<?xml version="1.0" encoding="utf-8"?>
<entity id="5d5e29bc-4bdb-4182-ad8a-5f9091c06d9b" created="2020-08-18T17:59:42.1375277-06:00" model-type="Catfish.Core.Models.ItemTemplate, Catfish.Core, Version=1.0.0.0, Culture=neutral, PublicKeyToken=null">
  <name model-type="Catfish.Core.Models.Contents.MultilingualName, Catfish.Core, Version=1.0.0.0, Culture=neutral, PublicKeyToken=null" id="4f5561f1-64de-4ea3-834e-9f0e30e739f5">
    <text model-type="Catfish.Core.Models.Contents.Text, Catfish.Core, Version=1.0.0.0, Culture=neutral, PublicKeyToken=null" id="9c54ab66-56f8-4da1-a516-e67de07a0dc9" xml:lang="en">Calendar Management System Workflow</text>
  </name>
  <description model-type="Catfish.Core.Models.Contents.MultilingualDescription, Catfish.Core, Version=1.0.0.0, Culture=neutral, PublicKeyToken=null" id="31f9df9b-46d2-4384-abf3-f8ff81fea2a8" />
  <metadata-sets>
    <metadata-set model-type="Catfish.Core.Models.Contents.MetadataSet, Catfish.Core, Version=1.0.0.0, Culture=neutral, PublicKeyToken=null" id="0f20de83-3182-47bd-9bc7-b2ff0299260c" created="2020-08-18T17:59:42.1477966-06:00">
      <name model-type="Catfish.Core.Models.Contents.MultilingualName, Catfish.Core, Version=1.0.0.0, Culture=neutral, PublicKeyToken=null" id="4ed6819a-7840-4d0a-851a-5086ff671a10">
        <text model-type="Catfish.Core.Models.Contents.Text, Catfish.Core, Version=1.0.0.0, Culture=neutral, PublicKeyToken=null" id="6fd365cc-f89b-4116-bd92-05f55e710896" xml:lang="en">Central Admin Notification</text>
      </name>
      <description model-type="Catfish.Core.Models.Contents.MultilingualDescription, Catfish.Core, Version=1.0.0.0, Culture=neutral, PublicKeyToken=null" id="84a5267a-de83-42ff-aebc-d2a6076962da">
        <text model-type="Catfish.Core.Models.Contents.Text, Catfish.Core, Version=1.0.0.0, Culture=neutral, PublicKeyToken=null" id="3788a0c5-08d5-40de-99b9-656eda77bcdc" xml:lang="en">This metadata set defines the email template to be sent to the central admin when a dept admin makes a submission.</text>
      </description>
      <fields>
        <field model-type="Catfish.Core.Models.Contents.Fields.TextField, Catfish.Core, Version=1.0.0.0, Culture=neutral, PublicKeyToken=null" id="af25249c-8acf-432c-b410-aaabe42e57a9">
          <name model-type="Catfish.Core.Models.Contents.MultilingualName, Catfish.Core, Version=1.0.0.0, Culture=neutral, PublicKeyToken=null" id="fa4b828f-b3bf-4cf9-b678-b1a63a6f53b1">
            <text model-type="Catfish.Core.Models.Contents.Text, Catfish.Core, Version=1.0.0.0, Culture=neutral, PublicKeyToken=null" id="834d3c9e-75ff-4793-80f0-42772f911570" xml:lang="en">Subject</text>
          </name>
          <description model-type="Catfish.Core.Models.Contents.MultilingualDescription, Catfish.Core, Version=1.0.0.0, Culture=neutral, PublicKeyToken=null" id="4a9e03df-23e9-4f48-922e-8abd8bc819fe" />
          <values>
            <value model-type="Catfish.Core.Models.Contents.MultilingualValue, Catfish.Core, Version=1.0.0.0, Culture=neutral, PublicKeyToken=null" id="cf119dbe-19bb-4579-8065-4a6f83ee8a42">
              <text model-type="Catfish.Core.Models.Contents.Text, Catfish.Core, Version=1.0.0.0, Culture=neutral, PublicKeyToken=null" id="406b2030-b794-4515-8c5d-9e1b3096620f" xml:lang="en">Calendar Change Submission</text>
            </value>
          </values>
        </field>
        <field model-type="Catfish.Core.Models.Contents.Fields.TextArea, Catfish.Core, Version=1.0.0.0, Culture=neutral, PublicKeyToken=null" id="8e842c3f-0242-48ae-8957-51be5128e824">
          <name model-type="Catfish.Core.Models.Contents.MultilingualName, Catfish.Core, Version=1.0.0.0, Culture=neutral, PublicKeyToken=null" id="297e6be6-bf8d-45db-a2d8-41caf625a9f8">
            <text model-type="Catfish.Core.Models.Contents.Text, Catfish.Core, Version=1.0.0.0, Culture=neutral, PublicKeyToken=null" id="4685124c-72ec-4628-aa8b-506e6897e187" xml:lang="en">Body</text>
          </name>
          <description model-type="Catfish.Core.Models.Contents.MultilingualDescription, Catfish.Core, Version=1.0.0.0, Culture=neutral, PublicKeyToken=null" id="6f2fc092-93e2-49e2-a277-fcc901a2188f" />
          <values>
            <value model-type="Catfish.Core.Models.Contents.MultilingualValue, Catfish.Core, Version=1.0.0.0, Culture=neutral, PublicKeyToken=null" id="09204d53-bba7-4d32-976f-c0a02c853822">
              <text model-type="Catfish.Core.Models.Contents.Text, Catfish.Core, Version=1.0.0.0, Culture=neutral, PublicKeyToken=null" id="e9979dc7-b844-4de7-b0f1-f0c2a2777fb4" xml:lang="en">A @Link[calendar chane|@Model] was submitted.

Thank you</text>
            </value>
          </values>
        </field>
      </fields>
    </metadata-set>
    <metadata-set model-type="Catfish.Core.Models.Contents.MetadataSet, Catfish.Core, Version=1.0.0.0, Culture=neutral, PublicKeyToken=null" id="b3eef503-08d7-4fa0-acaf-3f6d34908f82" created="2020-08-18T17:59:42.1548385-06:00">
      <name model-type="Catfish.Core.Models.Contents.MultilingualName, Catfish.Core, Version=1.0.0.0, Culture=neutral, PublicKeyToken=null" id="d6ccf539-af92-4a9e-9db9-93cf9e6748d3">
        <text model-type="Catfish.Core.Models.Contents.Text, Catfish.Core, Version=1.0.0.0, Culture=neutral, PublicKeyToken=null" id="7a475998-e57d-46b0-877b-e516e7243db4" xml:lang="en">Dept. Admin Submission Admin Notification</text>
      </name>
      <description model-type="Catfish.Core.Models.Contents.MultilingualDescription, Catfish.Core, Version=1.0.0.0, Culture=neutral, PublicKeyToken=null" id="44d0bf8d-5618-4ca4-8eee-d1ad18251c72">
        <text model-type="Catfish.Core.Models.Contents.Text, Catfish.Core, Version=1.0.0.0, Culture=neutral, PublicKeyToken=null" id="f31ee0e5-5a85-448f-a70e-ad9b2659d811" xml:lang="en">This metadata set defines the email template to be sent to the dept admin when he/she submits a new or revised calendar change.</text>
      </description>
      <fields>
        <field model-type="Catfish.Core.Models.Contents.Fields.TextField, Catfish.Core, Version=1.0.0.0, Culture=neutral, PublicKeyToken=null" id="dde2afb2-25b0-439f-b313-186c97d2c4d9">
          <name model-type="Catfish.Core.Models.Contents.MultilingualName, Catfish.Core, Version=1.0.0.0, Culture=neutral, PublicKeyToken=null" id="b0b1cfc0-70e8-4e61-ba2f-62396919f8e5">
            <text model-type="Catfish.Core.Models.Contents.Text, Catfish.Core, Version=1.0.0.0, Culture=neutral, PublicKeyToken=null" id="d762565f-5a94-486b-83cf-23d3594b37a3" xml:lang="en">Subject</text>
          </name>
          <description model-type="Catfish.Core.Models.Contents.MultilingualDescription, Catfish.Core, Version=1.0.0.0, Culture=neutral, PublicKeyToken=null" id="aa1a7ecd-f900-420f-bc30-2aaff18dae88" />
          <values>
            <value model-type="Catfish.Core.Models.Contents.MultilingualValue, Catfish.Core, Version=1.0.0.0, Culture=neutral, PublicKeyToken=null" id="88c590bc-b324-4c92-8b6d-f210d022e321">
              <text model-type="Catfish.Core.Models.Contents.Text, Catfish.Core, Version=1.0.0.0, Culture=neutral, PublicKeyToken=null" id="952b2c23-9352-4a45-98a8-d7f9a86278d8" xml:lang="en">Calendar Change Submission</text>
            </value>
          </values>
        </field>
        <field model-type="Catfish.Core.Models.Contents.Fields.TextArea, Catfish.Core, Version=1.0.0.0, Culture=neutral, PublicKeyToken=null" id="dc9fe0e7-2628-467e-b224-2ff6458247d1">
          <name model-type="Catfish.Core.Models.Contents.MultilingualName, Catfish.Core, Version=1.0.0.0, Culture=neutral, PublicKeyToken=null" id="e5975382-6cd7-4bc9-aa15-e86f15ea2d42">
            <text model-type="Catfish.Core.Models.Contents.Text, Catfish.Core, Version=1.0.0.0, Culture=neutral, PublicKeyToken=null" id="fdffbc1b-04e3-49d3-a407-7c788d6ea560" xml:lang="en">Body</text>
          </name>
          <description model-type="Catfish.Core.Models.Contents.MultilingualDescription, Catfish.Core, Version=1.0.0.0, Culture=neutral, PublicKeyToken=null" id="bd186f71-a92b-4a13-be33-b9c12a6bd300" />
          <values>
            <value model-type="Catfish.Core.Models.Contents.MultilingualValue, Catfish.Core, Version=1.0.0.0, Culture=neutral, PublicKeyToken=null" id="d7c59cfa-6a70-4143-b04f-52b225431a08">
              <text model-type="Catfish.Core.Models.Contents.Text, Catfish.Core, Version=1.0.0.0, Culture=neutral, PublicKeyToken=null" id="e496fe00-075a-4223-b3cc-16e2c3b48f6c" xml:lang="en">A @Link[calendar change|@Model] was submitted.

Thank you</text>
            </value>
          </values>
        </field>
      </fields>
    </metadata-set>
    <metadata-set model-type="Catfish.Core.Models.Contents.MetadataSet, Catfish.Core, Version=1.0.0.0, Culture=neutral, PublicKeyToken=null" id="5c569995-c69a-4790-8dd0-0c924892c840" created="2020-08-18T17:59:42.155174-06:00">
      <name model-type="Catfish.Core.Models.Contents.MultilingualName, Catfish.Core, Version=1.0.0.0, Culture=neutral, PublicKeyToken=null" id="78c260e6-d1ab-4d29-9444-e2437d075239">
        <text model-type="Catfish.Core.Models.Contents.Text, Catfish.Core, Version=1.0.0.0, Culture=neutral, PublicKeyToken=null" id="e00b75fe-dba1-4521-a12b-baaccf8fc89d" xml:lang="en">Central Admin Revision Notification</text>
      </name>
      <description model-type="Catfish.Core.Models.Contents.MultilingualDescription, Catfish.Core, Version=1.0.0.0, Culture=neutral, PublicKeyToken=null" id="58530805-df7e-4066-9f52-c890c0f59e71">
        <text model-type="Catfish.Core.Models.Contents.Text, Catfish.Core, Version=1.0.0.0, Culture=neutral, PublicKeyToken=null" id="40dfe11b-ac2f-4b9d-bc0b-92f162630e5d" xml:lang="en">This metadata set defines the email template to be sent to the dept admin when central admin make a revision request.</text>
      </description>
      <fields>
        <field model-type="Catfish.Core.Models.Contents.Fields.TextField, Catfish.Core, Version=1.0.0.0, Culture=neutral, PublicKeyToken=null" id="54e53c3f-fd3f-464d-885a-d8d18f7ae2fc">
          <name model-type="Catfish.Core.Models.Contents.MultilingualName, Catfish.Core, Version=1.0.0.0, Culture=neutral, PublicKeyToken=null" id="c8a065c4-9161-4e15-be32-6d01c831bd6d">
            <text model-type="Catfish.Core.Models.Contents.Text, Catfish.Core, Version=1.0.0.0, Culture=neutral, PublicKeyToken=null" id="fe4c6cb3-8906-49c0-973f-1661329e1b52" xml:lang="en">Subject</text>
          </name>
          <description model-type="Catfish.Core.Models.Contents.MultilingualDescription, Catfish.Core, Version=1.0.0.0, Culture=neutral, PublicKeyToken=null" id="7364dc7a-0fa8-449c-8ca9-5a2f9f3305fb" />
          <values>
            <value model-type="Catfish.Core.Models.Contents.MultilingualValue, Catfish.Core, Version=1.0.0.0, Culture=neutral, PublicKeyToken=null" id="3e9fad1b-62ae-4a5f-a324-45ea23d85ca7">
              <text model-type="Catfish.Core.Models.Contents.Text, Catfish.Core, Version=1.0.0.0, Culture=neutral, PublicKeyToken=null" id="49c3fd78-a1ab-4ff0-b512-819ec6ffcdbd" xml:lang="en">Calendar Change Submission Need to Revise</text>
            </value>
          </values>
        </field>
        <field model-type="Catfish.Core.Models.Contents.Fields.TextArea, Catfish.Core, Version=1.0.0.0, Culture=neutral, PublicKeyToken=null" id="71e87017-3164-4f89-8022-aeebf790ff95">
          <name model-type="Catfish.Core.Models.Contents.MultilingualName, Catfish.Core, Version=1.0.0.0, Culture=neutral, PublicKeyToken=null" id="78385811-9a09-405c-bf8f-b168356a9b71">
            <text model-type="Catfish.Core.Models.Contents.Text, Catfish.Core, Version=1.0.0.0, Culture=neutral, PublicKeyToken=null" id="645436e8-6413-4fb2-9acb-c68dab38de3c" xml:lang="en">Body</text>
          </name>
          <description model-type="Catfish.Core.Models.Contents.MultilingualDescription, Catfish.Core, Version=1.0.0.0, Culture=neutral, PublicKeyToken=null" id="25c307ba-8f31-4f08-a269-6ea761a5e33e" />
          <values>
            <value model-type="Catfish.Core.Models.Contents.MultilingualValue, Catfish.Core, Version=1.0.0.0, Culture=neutral, PublicKeyToken=null" id="5e37b9b1-9d80-42f5-be14-5cf2eccfedba">
              <text model-type="Catfish.Core.Models.Contents.Text, Catfish.Core, Version=1.0.0.0, Culture=neutral, PublicKeyToken=null" id="e0b015c6-1ccc-4b8f-b0c6-e7aa33f6481b" xml:lang="en">A @Link[calendar change|@Model] need to revise.

Thank you</text>
            </value>
          </values>
        </field>
      </fields>
    </metadata-set>
    <metadata-set model-type="Catfish.Core.Models.Contents.MetadataSet, Catfish.Core, Version=1.0.0.0, Culture=neutral, PublicKeyToken=null" id="fe74148b-0aed-4ab7-b300-dc4f99cac4c4" created="2020-08-18T17:59:42.155296-06:00">
      <name model-type="Catfish.Core.Models.Contents.MultilingualName, Catfish.Core, Version=1.0.0.0, Culture=neutral, PublicKeyToken=null" id="f6a0e1b5-06e0-4c0b-9143-adf512d1cf2d">
        <text model-type="Catfish.Core.Models.Contents.Text, Catfish.Core, Version=1.0.0.0, Culture=neutral, PublicKeyToken=null" id="8a712173-b12d-4b54-a4ab-6e3b29a9efb2" xml:lang="en">Move to Draft Calendar Notification</text>
      </name>
      <description model-type="Catfish.Core.Models.Contents.MultilingualDescription, Catfish.Core, Version=1.0.0.0, Culture=neutral, PublicKeyToken=null" id="e38e72b6-690f-4136-80bc-288f2558cb27">
        <text model-type="Catfish.Core.Models.Contents.Text, Catfish.Core, Version=1.0.0.0, Culture=neutral, PublicKeyToken=null" id="75dc25f0-4f18-43bd-b764-627517f72a79" xml:lang="en">This metadata set defines the email template to be sent to the dept admin when the submission request move to the draft calendar.</text>
      </description>
      <fields>
        <field model-type="Catfish.Core.Models.Contents.Fields.TextField, Catfish.Core, Version=1.0.0.0, Culture=neutral, PublicKeyToken=null" id="90bced45-b6c7-4d05-9624-61949302057b">
          <name model-type="Catfish.Core.Models.Contents.MultilingualName, Catfish.Core, Version=1.0.0.0, Culture=neutral, PublicKeyToken=null" id="d2af073a-6c69-4fe1-84ba-12df077ad738">
            <text model-type="Catfish.Core.Models.Contents.Text, Catfish.Core, Version=1.0.0.0, Culture=neutral, PublicKeyToken=null" id="028f53da-f1d0-4094-97ab-8db2e9122986" xml:lang="en">Subject</text>
          </name>
          <description model-type="Catfish.Core.Models.Contents.MultilingualDescription, Catfish.Core, Version=1.0.0.0, Culture=neutral, PublicKeyToken=null" id="242901ee-f411-4cfd-a5ba-3d2b8b4a0603" />
          <values>
            <value model-type="Catfish.Core.Models.Contents.MultilingualValue, Catfish.Core, Version=1.0.0.0, Culture=neutral, PublicKeyToken=null" id="08d77aff-952f-4df4-b27b-aba9c5bc8697">
              <text model-type="Catfish.Core.Models.Contents.Text, Catfish.Core, Version=1.0.0.0, Culture=neutral, PublicKeyToken=null" id="2b734e5d-28e3-4b9a-8d70-7cdf7bd0b486" xml:lang="en">Calendar Change Submission moved to the draft calendar</text>
            </value>
          </values>
        </field>
        <field model-type="Catfish.Core.Models.Contents.Fields.TextArea, Catfish.Core, Version=1.0.0.0, Culture=neutral, PublicKeyToken=null" id="2244881b-3e17-46be-a1a8-2a62dcfdc559">
          <name model-type="Catfish.Core.Models.Contents.MultilingualName, Catfish.Core, Version=1.0.0.0, Culture=neutral, PublicKeyToken=null" id="97b1b1af-da50-45fd-97ab-d13fa15866cf">
            <text model-type="Catfish.Core.Models.Contents.Text, Catfish.Core, Version=1.0.0.0, Culture=neutral, PublicKeyToken=null" id="c57ca85f-b768-4a5a-a647-90ad4fc40632" xml:lang="en">Body</text>
          </name>
          <description model-type="Catfish.Core.Models.Contents.MultilingualDescription, Catfish.Core, Version=1.0.0.0, Culture=neutral, PublicKeyToken=null" id="9700cf0e-798d-4a0e-9d1c-6d4d5a3e2516" />
          <values>
            <value model-type="Catfish.Core.Models.Contents.MultilingualValue, Catfish.Core, Version=1.0.0.0, Culture=neutral, PublicKeyToken=null" id="215c1bb5-73e8-4f20-aaf8-d056338ec97c">
              <text model-type="Catfish.Core.Models.Contents.Text, Catfish.Core, Version=1.0.0.0, Culture=neutral, PublicKeyToken=null" id="cc0706d2-d15d-4eea-b652-60170b12245a" xml:lang="en">A @Link[calendar change|@Model] moved to the draft calendar.

Thank you</text>
            </value>
          </values>
        </field>
      </fields>
    </metadata-set>
  </metadata-sets>
  <data-container>
    <data-item model-type="Catfish.Core.Models.Contents.Data.DataItem, Catfish.Core, Version=1.0.0.0, Culture=neutral, PublicKeyToken=null" id="5a207b5e-db6c-4142-8e12-703b607bf581" created="2020-08-18T17:59:42.156216-06:00" is-root="true">
      <name model-type="Catfish.Core.Models.Contents.MultilingualName, Catfish.Core, Version=1.0.0.0, Culture=neutral, PublicKeyToken=null" id="bee1853d-ad28-403f-b119-79ee177aeb6f">
        <text model-type="Catfish.Core.Models.Contents.Text, Catfish.Core, Version=1.0.0.0, Culture=neutral, PublicKeyToken=null" id="305b3457-d6b1-456f-ab67-cc6a5251fec7" xml:lang="en">Calendar Change Request</text>
      </name>
      <description model-type="Catfish.Core.Models.Contents.MultilingualDescription, Catfish.Core, Version=1.0.0.0, Culture=neutral, PublicKeyToken=null" id="43f66636-681e-4786-b125-31246a1824dc">
        <text model-type="Catfish.Core.Models.Contents.Text, Catfish.Core, Version=1.0.0.0, Culture=neutral, PublicKeyToken=null" id="70114f98-4bb9-46f4-9a2f-b5e08dad5b8e" xml:lang="en">This is the form to be filled by the department admin when a calndar change is requested.</text>
      </description>
      <fields>
        <field model-type="Catfish.Core.Models.Contents.Fields.TextField, Catfish.Core, Version=1.0.0.0, Culture=neutral, PublicKeyToken=null" id="e5eb9e3d-3888-49a4-8514-18c0b01ffb3c" required="true">
          <name model-type="Catfish.Core.Models.Contents.MultilingualName, Catfish.Core, Version=1.0.0.0, Culture=neutral, PublicKeyToken=null" id="5ef37f2d-12e6-4252-a163-f2c37af22450">
            <text model-type="Catfish.Core.Models.Contents.Text, Catfish.Core, Version=1.0.0.0, Culture=neutral, PublicKeyToken=null" id="046fb7a3-9e1f-4d97-b221-d0e41f3b75c2" xml:lang="en">Course Name</text>
          </name>
          <description model-type="Catfish.Core.Models.Contents.MultilingualDescription, Catfish.Core, Version=1.0.0.0, Culture=neutral, PublicKeyToken=null" id="3226bbb4-edee-4158-b5f6-f8948ccb00bb" />
          <values>
            <value model-type="Catfish.Core.Models.Contents.MultilingualValue, Catfish.Core, Version=1.0.0.0, Culture=neutral, PublicKeyToken=null" id="67df0efb-a699-4443-bc9f-f4575632e472">
              <text model-type="Catfish.Core.Models.Contents.Text, Catfish.Core, Version=1.0.0.0, Culture=neutral, PublicKeyToken=null" id="67ee80b2-f2d7-42a2-bd3c-bf7878b62f57" xml:lang="en"></text>
            </value>
          </values>
        </field>
        <field model-type="Catfish.Core.Models.Contents.Fields.TextField, Catfish.Core, Version=1.0.0.0, Culture=neutral, PublicKeyToken=null" id="f0bf1d0a-6ae3-4266-b1ff-e3514a4f0947" required="true">
          <name model-type="Catfish.Core.Models.Contents.MultilingualName, Catfish.Core, Version=1.0.0.0, Culture=neutral, PublicKeyToken=null" id="9321a82a-1aef-41d2-99c2-9f4a83e12f3d">
            <text model-type="Catfish.Core.Models.Contents.Text, Catfish.Core, Version=1.0.0.0, Culture=neutral, PublicKeyToken=null" id="5176fd07-63b8-4133-b32c-6bc6d78f37d2" xml:lang="en">Course Number</text>
          </name>
          <description model-type="Catfish.Core.Models.Contents.MultilingualDescription, Catfish.Core, Version=1.0.0.0, Culture=neutral, PublicKeyToken=null" id="566a7370-dbb3-4ec9-af72-b0917961a3f8" />
          <values>
            <value model-type="Catfish.Core.Models.Contents.MultilingualValue, Catfish.Core, Version=1.0.0.0, Culture=neutral, PublicKeyToken=null" id="e64f3928-6eac-424b-aed6-4d8b9a22ac98">
              <text model-type="Catfish.Core.Models.Contents.Text, Catfish.Core, Version=1.0.0.0, Culture=neutral, PublicKeyToken=null" id="7c4052ae-538f-4349-837a-cbf072edb81e" xml:lang="en"></text>
            </value>
          </values>
        </field>
        <field model-type="Catfish.Core.Models.Contents.Fields.TextArea, Catfish.Core, Version=1.0.0.0, Culture=neutral, PublicKeyToken=null" id="f6559354-4cd4-41ab-a330-01768a8834d1" required="true">
          <name model-type="Catfish.Core.Models.Contents.MultilingualName, Catfish.Core, Version=1.0.0.0, Culture=neutral, PublicKeyToken=null" id="d271b2c5-75e6-4f58-a500-b0a5aeec4f25">
            <text model-type="Catfish.Core.Models.Contents.Text, Catfish.Core, Version=1.0.0.0, Culture=neutral, PublicKeyToken=null" id="4265d17f-58cb-4737-975f-8be9bafb09df" xml:lang="en">Change Description</text>
          </name>
          <description model-type="Catfish.Core.Models.Contents.MultilingualDescription, Catfish.Core, Version=1.0.0.0, Culture=neutral, PublicKeyToken=null" id="a87b9f22-a604-4662-8674-9f86d67858cf" />
          <values>
            <value model-type="Catfish.Core.Models.Contents.MultilingualValue, Catfish.Core, Version=1.0.0.0, Culture=neutral, PublicKeyToken=null" id="6f8838b2-d625-4496-96e5-c7c855cefa80">
              <text model-type="Catfish.Core.Models.Contents.Text, Catfish.Core, Version=1.0.0.0, Culture=neutral, PublicKeyToken=null" id="eb05e6d1-b7e8-4c5f-81ca-199110232d0f" xml:lang="en"></text>
            </value>
          </values>
        </field>
      </fields>
    </data-item>
    <data-item model-type="Catfish.Core.Models.Contents.Data.DataItem, Catfish.Core, Version=1.0.0.0, Culture=neutral, PublicKeyToken=null" id="8c12cd83-0c37-4949-87f1-ceed634b6036" created="2020-08-18T17:59:42.1574963-06:00" is-root="true">
      <name model-type="Catfish.Core.Models.Contents.MultilingualName, Catfish.Core, Version=1.0.0.0, Culture=neutral, PublicKeyToken=null" id="be8b1bcd-280d-4c60-a66c-a0e39545b38e">
        <text model-type="Catfish.Core.Models.Contents.Text, Catfish.Core, Version=1.0.0.0, Culture=neutral, PublicKeyToken=null" id="7e9e0ba5-a16c-46e2-8264-58ae4f113362" xml:lang="en">Submission Revise Request</text>
      </name>
      <description model-type="Catfish.Core.Models.Contents.MultilingualDescription, Catfish.Core, Version=1.0.0.0, Culture=neutral, PublicKeyToken=null" id="8e736651-214d-4f2e-8b03-a2483071b602">
        <text model-type="Catfish.Core.Models.Contents.Text, Catfish.Core, Version=1.0.0.0, Culture=neutral, PublicKeyToken=null" id="0824a3d7-8c59-400e-94e9-e314be202bfd" xml:lang="en">This is the form to be filled by the central admin when a submission revision is requested.</text>
      </description>
      <fields>
        <field model-type="Catfish.Core.Models.Contents.Fields.TextField, Catfish.Core, Version=1.0.0.0, Culture=neutral, PublicKeyToken=null" id="a58184d8-21e2-4dd3-a16f-d0a138865d99" required="true">
          <name model-type="Catfish.Core.Models.Contents.MultilingualName, Catfish.Core, Version=1.0.0.0, Culture=neutral, PublicKeyToken=null" id="469ac744-9a3d-4c6e-b995-a77a6af867d6">
            <text model-type="Catfish.Core.Models.Contents.Text, Catfish.Core, Version=1.0.0.0, Culture=neutral, PublicKeyToken=null" id="0eeedddd-37ec-46fc-9971-827edd582375" xml:lang="en">Course Name</text>
          </name>
          <description model-type="Catfish.Core.Models.Contents.MultilingualDescription, Catfish.Core, Version=1.0.0.0, Culture=neutral, PublicKeyToken=null" id="105592d2-19d8-491c-8af9-3110d369a523" />
          <values>
            <value model-type="Catfish.Core.Models.Contents.MultilingualValue, Catfish.Core, Version=1.0.0.0, Culture=neutral, PublicKeyToken=null" id="2f08f717-bb9b-44b4-a0a3-4f2b2f3204e8">
              <text model-type="Catfish.Core.Models.Contents.Text, Catfish.Core, Version=1.0.0.0, Culture=neutral, PublicKeyToken=null" id="b30e286f-ac6e-41ce-a500-85ec8f4a0af4" xml:lang="en"></text>
            </value>
          </values>
        </field>
        <field model-type="Catfish.Core.Models.Contents.Fields.TextField, Catfish.Core, Version=1.0.0.0, Culture=neutral, PublicKeyToken=null" id="121522b1-aa6e-42c9-9837-1ef6ff08858e" required="true">
          <name model-type="Catfish.Core.Models.Contents.MultilingualName, Catfish.Core, Version=1.0.0.0, Culture=neutral, PublicKeyToken=null" id="570464e3-6ff1-4e71-975f-c75305cce4e2">
            <text model-type="Catfish.Core.Models.Contents.Text, Catfish.Core, Version=1.0.0.0, Culture=neutral, PublicKeyToken=null" id="ce32a489-c47b-4d7b-8c37-899fc7b2c785" xml:lang="en">Course Number</text>
          </name>
          <description model-type="Catfish.Core.Models.Contents.MultilingualDescription, Catfish.Core, Version=1.0.0.0, Culture=neutral, PublicKeyToken=null" id="b7e190bc-cff3-4e46-982d-d63627800fc3" />
          <values>
            <value model-type="Catfish.Core.Models.Contents.MultilingualValue, Catfish.Core, Version=1.0.0.0, Culture=neutral, PublicKeyToken=null" id="9beb0862-9c18-44f5-b165-1b7a32678ea6">
              <text model-type="Catfish.Core.Models.Contents.Text, Catfish.Core, Version=1.0.0.0, Culture=neutral, PublicKeyToken=null" id="4aac1b1c-6ac5-4269-b6d6-1b5e74040494" xml:lang="en"></text>
            </value>
          </values>
        </field>
        <field model-type="Catfish.Core.Models.Contents.Fields.TextArea, Catfish.Core, Version=1.0.0.0, Culture=neutral, PublicKeyToken=null" id="570e5cf0-e941-4442-bcab-48077e70f102" required="true">
          <name model-type="Catfish.Core.Models.Contents.MultilingualName, Catfish.Core, Version=1.0.0.0, Culture=neutral, PublicKeyToken=null" id="dc2e76e6-1640-4166-b20f-9b91c1d6ae4c">
            <text model-type="Catfish.Core.Models.Contents.Text, Catfish.Core, Version=1.0.0.0, Culture=neutral, PublicKeyToken=null" id="b73944c2-7138-4571-a95f-b36f7fc3d7f1" xml:lang="en">Comments</text>
          </name>
          <description model-type="Catfish.Core.Models.Contents.MultilingualDescription, Catfish.Core, Version=1.0.0.0, Culture=neutral, PublicKeyToken=null" id="025eed9e-93dc-4473-9862-2325c74cd989" />
          <values>
            <value model-type="Catfish.Core.Models.Contents.MultilingualValue, Catfish.Core, Version=1.0.0.0, Culture=neutral, PublicKeyToken=null" id="f5346016-09ce-4b41-88a1-ef6cd8607278">
              <text model-type="Catfish.Core.Models.Contents.Text, Catfish.Core, Version=1.0.0.0, Culture=neutral, PublicKeyToken=null" id="53db7c37-ad6a-4655-aff2-e43413858dd5" xml:lang="en"></text>
            </value>
          </values>
        </field>
      </fields>
    </data-item>
  </data-container>
  <workflow model-type="Catfish.Core.Models.Contents.Workflow.Workflow, Catfish.Core, Version=1.0.0.0, Culture=neutral, PublicKeyToken=null" id="abbaf239-d491-42b0-a76f-6a1b412363fc">
    <states>
      <state model-type="Catfish.Core.Models.Contents.Workflow.State, Catfish.Core, Version=1.0.0.0, Culture=neutral, PublicKeyToken=null" id="0341a706-2266-4b89-a529-7d6122c30f04"></state>
      <state model-type="Catfish.Core.Models.Contents.Workflow.State, Catfish.Core, Version=1.0.0.0, Culture=neutral, PublicKeyToken=null" id="99c282ec-facf-4162-a615-fbf4d4881f27">Saved</state>
      <state model-type="Catfish.Core.Models.Contents.Workflow.State, Catfish.Core, Version=1.0.0.0, Culture=neutral, PublicKeyToken=null" id="84226058-b83c-4798-87de-d0750968dea5">Submitted</state>
      <state model-type="Catfish.Core.Models.Contents.Workflow.State, Catfish.Core, Version=1.0.0.0, Culture=neutral, PublicKeyToken=null" id="85c1a6c0-6a48-4498-9de3-f7441c02a1bc">Deleted</state>
      <state model-type="Catfish.Core.Models.Contents.Workflow.State, Catfish.Core, Version=1.0.0.0, Culture=neutral, PublicKeyToken=null" id="75464e92-a950-4ac4-9cfe-b3aeddeb2bd8">DeanOfficeRevision</state>
      <state model-type="Catfish.Core.Models.Contents.Workflow.State, Catfish.Core, Version=1.0.0.0, Culture=neutral, PublicKeyToken=null" id="3d73e38f-8b6a-4d71-bae1-f532de3fd67c">DeanOfficeRevisionCompleted</state>
      <state model-type="Catfish.Core.Models.Contents.Workflow.State, Catfish.Core, Version=1.0.0.0, Culture=neutral, PublicKeyToken=null" id="d0289864-7c3a-4394-866a-e472a6ea030d">SavedDeanOfficeRevision</state>
      <state model-type="Catfish.Core.Models.Contents.Workflow.State, Catfish.Core, Version=1.0.0.0, Culture=neutral, PublicKeyToken=null" id="dd21505a-f54a-4ef7-9e6e-979132dfda36">WithAAC</state>
      <state model-type="Catfish.Core.Models.Contents.Workflow.State, Catfish.Core, Version=1.0.0.0, Culture=neutral, PublicKeyToken=null" id="ac42d52b-3fed-4770-9fbd-d9d5ed5d9510">AACRevision</state>
      <state model-type="Catfish.Core.Models.Contents.Workflow.State, Catfish.Core, Version=1.0.0.0, Culture=neutral, PublicKeyToken=null" id="643129b1-b5a8-4f2e-ae70-79baffc79235">SavedAACRevision</state>
      <state model-type="Catfish.Core.Models.Contents.Workflow.State, Catfish.Core, Version=1.0.0.0, Culture=neutral, PublicKeyToken=null" id="4a1c34cc-2e55-4301-9bf5-a87a5ed244f1">AACRevisionCompleted</state>
      <state model-type="Catfish.Core.Models.Contents.Workflow.State, Catfish.Core, Version=1.0.0.0, Culture=neutral, PublicKeyToken=null" id="c4ada4ca-7a2d-4831-8ab7-8c8bcff03117">AACApproved</state>
      <state model-type="Catfish.Core.Models.Contents.Workflow.State, Catfish.Core, Version=1.0.0.0, Culture=neutral, PublicKeyToken=null" id="db5cec7f-9b35-4d1d-9eac-f722744c9433">WithAEC</state>
      <state model-type="Catfish.Core.Models.Contents.Workflow.State, Catfish.Core, Version=1.0.0.0, Culture=neutral, PublicKeyToken=null" id="7d1eeaf9-fbb4-42cd-83e4-ea6644c68a2c">AECRevision</state>
      <state model-type="Catfish.Core.Models.Contents.Workflow.State, Catfish.Core, Version=1.0.0.0, Culture=neutral, PublicKeyToken=null" id="467da058-6fb6-4091-b107-4837c2590033">SavedAECRevision</state>
      <state model-type="Catfish.Core.Models.Contents.Workflow.State, Catfish.Core, Version=1.0.0.0, Culture=neutral, PublicKeyToken=null" id="0f53d2e0-c039-4f24-bae1-99b2cf16d408">AECRevisionCompleted</state>
      <state model-type="Catfish.Core.Models.Contents.Workflow.State, Catfish.Core, Version=1.0.0.0, Culture=neutral, PublicKeyToken=null" id="408ac0a0-31fd-4cc9-b42a-204e8aeca427">AECApproved</state>
      <state model-type="Catfish.Core.Models.Contents.Workflow.State, Catfish.Core, Version=1.0.0.0, Culture=neutral, PublicKeyToken=null" id="78d3fea4-718b-4321-b22e-10caeec498fc">WithAFC</state>
      <state model-type="Catfish.Core.Models.Contents.Workflow.State, Catfish.Core, Version=1.0.0.0, Culture=neutral, PublicKeyToken=null" id="0b1f4a6f-bb5e-47e6-9a14-ea303d79f9af">AFCRevision</state>
      <state model-type="Catfish.Core.Models.Contents.Workflow.State, Catfish.Core, Version=1.0.0.0, Culture=neutral, PublicKeyToken=null" id="ab79e502-c919-46bb-bc6b-16999ae9cb7b">SavedAFCRevision</state>
      <state model-type="Catfish.Core.Models.Contents.Workflow.State, Catfish.Core, Version=1.0.0.0, Culture=neutral, PublicKeyToken=null" id="6873f55f-4bc5-4fa3-a797-f3c838d5d98e">AFCRevisionCompleted</state>
      <state model-type="Catfish.Core.Models.Contents.Workflow.State, Catfish.Core, Version=1.0.0.0, Culture=neutral, PublicKeyToken=null" id="8e6bb279-3a85-4892-a543-c375bf611aaf">AFCApproved</state>
      <state model-type="Catfish.Core.Models.Contents.Workflow.State, Catfish.Core, Version=1.0.0.0, Culture=neutral, PublicKeyToken=null" id="9e1956da-37bf-4bca-a577-ba561e08ff7a">WithGFC</state>
      <state model-type="Catfish.Core.Models.Contents.Workflow.State, Catfish.Core, Version=1.0.0.0, Culture=neutral, PublicKeyToken=null" id="ae1edcbc-daf1-4103-a7eb-c26cc89e1f70">GFCRevision</state>
      <state model-type="Catfish.Core.Models.Contents.Workflow.State, Catfish.Core, Version=1.0.0.0, Culture=neutral, PublicKeyToken=null" id="b64f4bc2-6759-49dd-9316-06563b8be43d">SavedGFCRevision</state>
      <state model-type="Catfish.Core.Models.Contents.Workflow.State, Catfish.Core, Version=1.0.0.0, Culture=neutral, PublicKeyToken=null" id="f62f14e0-58a8-490a-8862-4292b323e699">GFCRevisionCompleted</state>
      <state model-type="Catfish.Core.Models.Contents.Workflow.State, Catfish.Core, Version=1.0.0.0, Culture=neutral, PublicKeyToken=null" id="b968f9d5-0942-4c07-8f97-062ef4cd6b6b">GFCApproved</state>
      <state model-type="Catfish.Core.Models.Contents.Workflow.State, Catfish.Core, Version=1.0.0.0, Culture=neutral, PublicKeyToken=null" id="e13337a0-d429-4e70-9aea-7f6d4aca20db">MoveToDraftError</state>
      <state model-type="Catfish.Core.Models.Contents.Workflow.State, Catfish.Core, Version=1.0.0.0, Culture=neutral, PublicKeyToken=null" id="1a283c22-330e-4faf-9b32-fcbd8b98db80">MoveToDraftCorrect</state>
    </states>
    <roles>
      <role model-type="Catfish.Core.Models.Contents.Workflow.WorkflowRole, Catfish.Core, Version=1.0.0.0, Culture=neutral, PublicKeyToken=null" id="130ef6d9-033c-45b5-90d6-8c0c9ab5c50f">CentralAdmin</role>
      <role model-type="Catfish.Core.Models.Contents.Workflow.WorkflowRole, Catfish.Core, Version=1.0.0.0, Culture=neutral, PublicKeyToken=null" id="0f9b9e8e-ad62-478d-ad7f-ed3016c89924">DepartmentlAdmin</role>
      <role model-type="Catfish.Core.Models.Contents.Workflow.WorkflowRole, Catfish.Core, Version=1.0.0.0, Culture=neutral, PublicKeyToken=null" id="99751826-cfb9-40b0-88e0-320f54c37af0">Owner</role>
    </roles>
    <users>
      <user model-type="Catfish.Core.Models.Contents.Workflow.WorkflowUser, Catfish.Core, Version=1.0.0.0, Culture=neutral, PublicKeyToken=null" id="c4ae15a8-a5db-459b-ad69-5e0e209f47dd" email="centraladmin@ualberta.ca">
        <roles>
          <role-ref model-type="Catfish.Core.Models.Contents.Workflow.RoleReference, Catfish.Core, Version=1.0.0.0, Culture=neutral, PublicKeyToken=null" id="ec65b700-6e06-4867-9c70-ca4685fb1858" ref-id="130ef6d9-033c-45b5-90d6-8c0c9ab5c50f" />
        </roles>
      </user>
      <user model-type="Catfish.Core.Models.Contents.Workflow.WorkflowUser, Catfish.Core, Version=1.0.0.0, Culture=neutral, PublicKeyToken=null" id="d53c24f2-f9cd-481b-bdd6-239879215e8e" email="departmentadmin1@ualberta.ca">
        <roles>
          <role-ref model-type="Catfish.Core.Models.Contents.Workflow.RoleReference, Catfish.Core, Version=1.0.0.0, Culture=neutral, PublicKeyToken=null" id="8a16ac02-c0d7-43a9-a7b6-611cc1430611" ref-id="0f9b9e8e-ad62-478d-ad7f-ed3016c89924" />
        </roles>
      </user>
      <user model-type="Catfish.Core.Models.Contents.Workflow.WorkflowUser, Catfish.Core, Version=1.0.0.0, Culture=neutral, PublicKeyToken=null" id="8bdbc11d-3fe6-4760-9f17-90471a9c8682" email="departmentadmin2@ualberta.ca">
        <roles>
          <role-ref model-type="Catfish.Core.Models.Contents.Workflow.RoleReference, Catfish.Core, Version=1.0.0.0, Culture=neutral, PublicKeyToken=null" id="d45c7dc8-340d-4eec-aaf8-d4a4e948ea6a" ref-id="0f9b9e8e-ad62-478d-ad7f-ed3016c89924" />
        </roles>
      </user>
    </users>
    <triggers>
      <trigger model-type="Catfish.Core.Models.Contents.Workflow.EmailTrigger, Catfish.Core, Version=1.0.0.0, Culture=neutral, PublicKeyToken=null" id="b96f4aaa-9f5d-4d29-9eac-b1a85d93de1c" name="ToCentralAdmin" function="SendEmail">
        <recipients>
          <recipient model-type="Catfish.Core.Models.Contents.Workflow.EmailRecipient, Catfish.Core, Version=1.0.0.0, Culture=neutral, PublicKeyToken=null" id="00602806-6ccf-4d4b-856a-70742ae03986" email="centraladmin@ualberta.ca" />
        </recipients>
        <email-templates>
          <email-template-ref model-type="Catfish.Core.Models.Contents.Workflow.EmailTemplateReference, Catfish.Core, Version=1.0.0.0, Culture=neutral, PublicKeyToken=null" id="4bbe5247-d950-46c3-8eb4-137a4ad96929" ref-id="0f20de83-3182-47bd-9bc7-b2ff0299260c" />
        </email-templates>
      </trigger>
      <trigger model-type="Catfish.Core.Models.Contents.Workflow.EmailTrigger, Catfish.Core, Version=1.0.0.0, Culture=neutral, PublicKeyToken=null" id="cf8f407a-10f7-41ac-a029-74f6586c4066" name="ToOwnerOnDocumentSubmission" function="SendEmail">
        <recipients>
          <recipient model-type="Catfish.Core.Models.Contents.Workflow.EmailRecipient, Catfish.Core, Version=1.0.0.0, Culture=neutral, PublicKeyToken=null" id="1bacb25b-c95e-4380-a8c0-a24ad04959a7" owner="true" />
        </recipients>
        <email-templates>
          <email-template-ref model-type="Catfish.Core.Models.Contents.Workflow.EmailTemplateReference, Catfish.Core, Version=1.0.0.0, Culture=neutral, PublicKeyToken=null" id="f74c9d7c-2457-4743-af2c-723d240f2dab" ref-id="b3eef503-08d7-4fa0-acaf-3f6d34908f82" />
        </email-templates>
      </trigger>
      <trigger model-type="Catfish.Core.Models.Contents.Workflow.EmailTrigger, Catfish.Core, Version=1.0.0.0, Culture=neutral, PublicKeyToken=null" id="6d2a206a-cfab-4cdc-a88c-901bea6b9f7f" name="ToOwnerOnDocumentRevision" function="SendEmail">
        <recipients>
          <recipient model-type="Catfish.Core.Models.Contents.Workflow.EmailRecipient, Catfish.Core, Version=1.0.0.0, Culture=neutral, PublicKeyToken=null" id="4199700f-2fd3-4b7d-a1ca-4c6bbdd3f930" owner="true" />
        </recipients>
        <email-templates>
          <email-template-ref model-type="Catfish.Core.Models.Contents.Workflow.EmailTemplateReference, Catfish.Core, Version=1.0.0.0, Culture=neutral, PublicKeyToken=null" id="aa3a10a0-f9ab-44bc-af40-979b53f0ce13" ref-id="5c569995-c69a-4790-8dd0-0c924892c840" />
        </email-templates>
      </trigger>
      <trigger model-type="Catfish.Core.Models.Contents.Workflow.EmailTrigger, Catfish.Core, Version=1.0.0.0, Culture=neutral, PublicKeyToken=null" id="27227101-529f-47c1-9b21-919bb4b9790a" name="ToOwnerOnMovedToDraftCalendar" function="SendEmail">
        <recipients>
          <recipient model-type="Catfish.Core.Models.Contents.Workflow.EmailRecipient, Catfish.Core, Version=1.0.0.0, Culture=neutral, PublicKeyToken=null" id="d831751d-4ace-4b46-bdd2-b19337ce7ded" owner="true" />
        </recipients>
        <email-templates>
          <email-template-ref model-type="Catfish.Core.Models.Contents.Workflow.EmailTemplateReference, Catfish.Core, Version=1.0.0.0, Culture=neutral, PublicKeyToken=null" id="ed834144-f7e5-4c95-8ec9-475400dcd0ec" ref-id="fe74148b-0aed-4ab7-b300-dc4f99cac4c4" />
        </email-templates>
      </trigger>
    </triggers>
    <actions>
      <get-action model-type="Catfish.Core.Models.Contents.Workflow.GetAction, Catfish.Core, Version=1.0.0.0, Culture=neutral, PublicKeyToken=null" id="5a766299-03d1-48e9-8793-1f0c039ad325" link-lable="Start Submission" function="Create" group="Home">
        <params>
          <param model-type="Catfish.Core.Models.Contents.Workflow.Param, Catfish.Core, Version=1.0.0.0, Culture=neutral, PublicKeyToken=null" id="3c7204e1-2d19-495e-aba0-4cf5fffb8b6e" template-id="5a207b5e-db6c-4142-8e12-703b607bf581" />
        </params>
        <post-actions>
          <post-action model-type="Catfish.Core.Models.Contents.Workflow.PostAction, Catfish.Core, Version=1.0.0.0, Culture=neutral, PublicKeyToken=null" id="cbe09b0b-e317-41fa-905e-a335e50a83b7" button-lable="Save" function="Save">
            <state-mappings>
              <mapping model-type="Catfish.Core.Models.Contents.Workflow.Mapping, Catfish.Core, Version=1.0.0.0, Culture=neutral, PublicKeyToken=null" id="da5af049-8c63-4d1e-89bb-72395d61ecb5" current="0341a706-2266-4b89-a529-7d6122c30f04" next="99c282ec-facf-4162-a615-fbf4d4881f27" button-label="Save" />
            </state-mappings>
            <pop-ups />
            <trigger-refs />
          </post-action>
          <post-action model-type="Catfish.Core.Models.Contents.Workflow.PostAction, Catfish.Core, Version=1.0.0.0, Culture=neutral, PublicKeyToken=null" id="b8a63763-d0c8-45cf-85ad-ae25a61b29c0" button-lable="Submit" function="Save">
            <state-mappings>
              <mapping model-type="Catfish.Core.Models.Contents.Workflow.Mapping, Catfish.Core, Version=1.0.0.0, Culture=neutral, PublicKeyToken=null" id="970ad673-1c16-40bc-a46e-c5d814ea96b9" current="0341a706-2266-4b89-a529-7d6122c30f04" next="84226058-b83c-4798-87de-d0750968dea5" button-label="Submit" />
            </state-mappings>
            <pop-ups>
              <pop-up model-type="Catfish.Core.Models.Contents.Workflow.PopUp, Catfish.Core, Version=1.0.0.0, Culture=neutral, PublicKeyToken=null" id="cc31d6a2-e052-4a86-8e71-daf6a2051ec6" title="WARNING: Submitting Document" message="Once submitted, you cannot update the document.">
                <buttons>
                  <button model-type="Catfish.Core.Models.Contents.Workflow.Button, Catfish.Core, Version=1.0.0.0, Culture=neutral, PublicKeyToken=null" id="6645e48a-4a1d-4004-9710-7130ab4e5db2" text="Yes, submit" return="true" />
                  <button model-type="Catfish.Core.Models.Contents.Workflow.Button, Catfish.Core, Version=1.0.0.0, Culture=neutral, PublicKeyToken=null" id="643c7a83-4619-4adb-95f9-7abeb5a47079" text="Cancel" return="false" />
                </buttons>
              </pop-up>
            </pop-ups>
            <trigger-refs>
              <trigger-ref model-type="Catfish.Core.Models.Contents.Workflow.TriggerRef, Catfish.Core, Version=1.0.0.0, Culture=neutral, PublicKeyToken=null" id="2f1a4822-9d02-40ee-86c2-dfc97b978368" order="0" ref-id="b96f4aaa-9f5d-4d29-9eac-b1a85d93de1c" />
              <trigger-ref model-type="Catfish.Core.Models.Contents.Workflow.TriggerRef, Catfish.Core, Version=1.0.0.0, Culture=neutral, PublicKeyToken=null" id="f35f0784-cbdf-447e-9811-048d381db710" order="1" ref-id="cf8f407a-10f7-41ac-a029-74f6586c4066" />
            </trigger-refs>
          </post-action>
        </post-actions>
        <states />
        <authorizations>
          <role-ref model-type="Catfish.Core.Models.Contents.Workflow.RoleReference, Catfish.Core, Version=1.0.0.0, Culture=neutral, PublicKeyToken=null" id="9a0055ca-748a-486b-a8a8-16ae86dc54fd" ref-id="0f9b9e8e-ad62-478d-ad7f-ed3016c89924" />
        </authorizations>
      </get-action>
      <get-action model-type="Catfish.Core.Models.Contents.Workflow.GetAction, Catfish.Core, Version=1.0.0.0, Culture=neutral, PublicKeyToken=null" id="3825378a-447d-434b-8b04-12dacdb135de" link-lable="Edit Submission" function="Edit" group="Details">
        <params />
        <post-actions>
          <post-action model-type="Catfish.Core.Models.Contents.Workflow.PostAction, Catfish.Core, Version=1.0.0.0, Culture=neutral, PublicKeyToken=null" id="9a262a71-8690-4edf-8965-4e1d879854c6" button-lable="Save" function="Save">
            <state-mappings>
              <mapping model-type="Catfish.Core.Models.Contents.Workflow.Mapping, Catfish.Core, Version=1.0.0.0, Culture=neutral, PublicKeyToken=null" id="6230adf3-2f3b-40cb-ab24-49e6e03ee8b0" current="99c282ec-facf-4162-a615-fbf4d4881f27" next="99c282ec-facf-4162-a615-fbf4d4881f27" button-label="Save" />
              <mapping model-type="Catfish.Core.Models.Contents.Workflow.Mapping, Catfish.Core, Version=1.0.0.0, Culture=neutral, PublicKeyToken=null" id="a46287ac-d1bc-44db-a77d-92e8717ccac9" current="75464e92-a950-4ac4-9cfe-b3aeddeb2bd8" next="d0289864-7c3a-4394-866a-e472a6ea030d" button-label="Save" />
              <mapping model-type="Catfish.Core.Models.Contents.Workflow.Mapping, Catfish.Core, Version=1.0.0.0, Culture=neutral, PublicKeyToken=null" id="6a4508a1-12a8-4752-804c-c3d08003dbf4" current="ac42d52b-3fed-4770-9fbd-d9d5ed5d9510" next="643129b1-b5a8-4f2e-ae70-79baffc79235" button-label="Save" />
              <mapping model-type="Catfish.Core.Models.Contents.Workflow.Mapping, Catfish.Core, Version=1.0.0.0, Culture=neutral, PublicKeyToken=null" id="01cadd37-8807-478c-9b73-ba6927011033" current="7d1eeaf9-fbb4-42cd-83e4-ea6644c68a2c" next="467da058-6fb6-4091-b107-4837c2590033" button-label="Save" />
              <mapping model-type="Catfish.Core.Models.Contents.Workflow.Mapping, Catfish.Core, Version=1.0.0.0, Culture=neutral, PublicKeyToken=null" id="c63b924e-95aa-4004-8f01-e5279c8977b5" current="0b1f4a6f-bb5e-47e6-9a14-ea303d79f9af" next="ab79e502-c919-46bb-bc6b-16999ae9cb7b" button-label="Save" />
              <mapping model-type="Catfish.Core.Models.Contents.Workflow.Mapping, Catfish.Core, Version=1.0.0.0, Culture=neutral, PublicKeyToken=null" id="bcb30508-61f1-4826-8d46-724ba50d7dfb" current="ae1edcbc-daf1-4103-a7eb-c26cc89e1f70" next="b64f4bc2-6759-49dd-9316-06563b8be43d" button-label="Save" />
            </state-mappings>
            <pop-ups />
            <trigger-refs />
          </post-action>
          <post-action model-type="Catfish.Core.Models.Contents.Workflow.PostAction, Catfish.Core, Version=1.0.0.0, Culture=neutral, PublicKeyToken=null" id="b150624d-3860-4c90-95b7-c9da74d90319" button-lable="Submit" function="Save">
            <state-mappings>
              <mapping model-type="Catfish.Core.Models.Contents.Workflow.Mapping, Catfish.Core, Version=1.0.0.0, Culture=neutral, PublicKeyToken=null" id="c4f97818-c0a6-4e67-98e4-5eb00475b1e2" current="99c282ec-facf-4162-a615-fbf4d4881f27" next="84226058-b83c-4798-87de-d0750968dea5" button-label="Submit" />
              <mapping model-type="Catfish.Core.Models.Contents.Workflow.Mapping, Catfish.Core, Version=1.0.0.0, Culture=neutral, PublicKeyToken=null" id="9db2e06e-1dff-40b4-907f-e462dc70e6e7" current="75464e92-a950-4ac4-9cfe-b3aeddeb2bd8" next="3d73e38f-8b6a-4d71-bae1-f532de3fd67c" button-label="Submit" />
              <mapping model-type="Catfish.Core.Models.Contents.Workflow.Mapping, Catfish.Core, Version=1.0.0.0, Culture=neutral, PublicKeyToken=null" id="629e7d14-cd23-4230-9ff9-1d075ef5d590" current="d0289864-7c3a-4394-866a-e472a6ea030d" next="3d73e38f-8b6a-4d71-bae1-f532de3fd67c" button-label="Submit" />
              <mapping model-type="Catfish.Core.Models.Contents.Workflow.Mapping, Catfish.Core, Version=1.0.0.0, Culture=neutral, PublicKeyToken=null" id="f4d69125-e704-4ef9-ab8c-be9ee9afe418" current="ac42d52b-3fed-4770-9fbd-d9d5ed5d9510" next="4a1c34cc-2e55-4301-9bf5-a87a5ed244f1" button-label="Submit" />
              <mapping model-type="Catfish.Core.Models.Contents.Workflow.Mapping, Catfish.Core, Version=1.0.0.0, Culture=neutral, PublicKeyToken=null" id="22a8a535-8829-45d5-b07b-efade1670b4f" current="643129b1-b5a8-4f2e-ae70-79baffc79235" next="4a1c34cc-2e55-4301-9bf5-a87a5ed244f1" button-label="Submit" />
              <mapping model-type="Catfish.Core.Models.Contents.Workflow.Mapping, Catfish.Core, Version=1.0.0.0, Culture=neutral, PublicKeyToken=null" id="e77f60c8-0914-4660-a4ca-e0cbce515670" current="7d1eeaf9-fbb4-42cd-83e4-ea6644c68a2c" next="0f53d2e0-c039-4f24-bae1-99b2cf16d408" button-label="Submit" />
              <mapping model-type="Catfish.Core.Models.Contents.Workflow.Mapping, Catfish.Core, Version=1.0.0.0, Culture=neutral, PublicKeyToken=null" id="242b4b02-5eee-4c36-8011-39b3828eee44" current="467da058-6fb6-4091-b107-4837c2590033" next="0f53d2e0-c039-4f24-bae1-99b2cf16d408" button-label="Submit" />
              <mapping model-type="Catfish.Core.Models.Contents.Workflow.Mapping, Catfish.Core, Version=1.0.0.0, Culture=neutral, PublicKeyToken=null" id="9fc9b571-720f-4805-9cdd-3317935f8765" current="0b1f4a6f-bb5e-47e6-9a14-ea303d79f9af" next="6873f55f-4bc5-4fa3-a797-f3c838d5d98e" button-label="Submit" />
              <mapping model-type="Catfish.Core.Models.Contents.Workflow.Mapping, Catfish.Core, Version=1.0.0.0, Culture=neutral, PublicKeyToken=null" id="59950de9-98c9-4bd3-88f9-c3a95ef627b4" current="ab79e502-c919-46bb-bc6b-16999ae9cb7b" next="6873f55f-4bc5-4fa3-a797-f3c838d5d98e" button-label="Submit" />
              <mapping model-type="Catfish.Core.Models.Contents.Workflow.Mapping, Catfish.Core, Version=1.0.0.0, Culture=neutral, PublicKeyToken=null" id="166ec991-274b-4a54-9260-5bbd9e94fb61" current="ae1edcbc-daf1-4103-a7eb-c26cc89e1f70" next="f62f14e0-58a8-490a-8862-4292b323e699" button-label="Submit" />
              <mapping model-type="Catfish.Core.Models.Contents.Workflow.Mapping, Catfish.Core, Version=1.0.0.0, Culture=neutral, PublicKeyToken=null" id="70cb19f1-6211-4890-a50e-a13073da8457" current="b64f4bc2-6759-49dd-9316-06563b8be43d" next="f62f14e0-58a8-490a-8862-4292b323e699" button-label="Submit" />
            </state-mappings>
            <pop-ups>
              <pop-up model-type="Catfish.Core.Models.Contents.Workflow.PopUp, Catfish.Core, Version=1.0.0.0, Culture=neutral, PublicKeyToken=null" id="55c63dce-7db5-45f4-bcaf-d9940ab0725e" title="WARNING: Submitting Document" message="Once submitted, you cannot update the document.">
                <buttons>
                  <button model-type="Catfish.Core.Models.Contents.Workflow.Button, Catfish.Core, Version=1.0.0.0, Culture=neutral, PublicKeyToken=null" id="85e1068f-02a0-4398-813d-f92f7ba55679" text="Yes, submit" return="true" />
                  <button model-type="Catfish.Core.Models.Contents.Workflow.Button, Catfish.Core, Version=1.0.0.0, Culture=neutral, PublicKeyToken=null" id="51c90c93-868a-4114-a2ac-cca63f39a2ae" text="Cancel" return="false" />
                </buttons>
              </pop-up>
            </pop-ups>
            <trigger-refs>
              <trigger-ref model-type="Catfish.Core.Models.Contents.Workflow.TriggerRef, Catfish.Core, Version=1.0.0.0, Culture=neutral, PublicKeyToken=null" id="9579ff74-0f14-49fa-ac77-fd7976c1b60f" order="0" ref-id="b96f4aaa-9f5d-4d29-9eac-b1a85d93de1c" />
              <trigger-ref model-type="Catfish.Core.Models.Contents.Workflow.TriggerRef, Catfish.Core, Version=1.0.0.0, Culture=neutral, PublicKeyToken=null" id="eabb1d83-8ae6-41d6-a877-7edc2a2ac32f" order="1" ref-id="cf8f407a-10f7-41ac-a029-74f6586c4066" />
            </trigger-refs>
          </post-action>
        </post-actions>
        <states>
          <state-ref model-type="Catfish.Core.Models.Contents.Workflow.StateRef, Catfish.Core, Version=1.0.0.0, Culture=neutral, PublicKeyToken=null" id="e795cd04-7c76-409c-8204-6d86bb3a5ffd" ref-id="99c282ec-facf-4162-a615-fbf4d4881f27" />
          <state-ref model-type="Catfish.Core.Models.Contents.Workflow.StateRef, Catfish.Core, Version=1.0.0.0, Culture=neutral, PublicKeyToken=null" id="99b633f1-6580-4542-9b18-014a285adcdf" ref-id="75464e92-a950-4ac4-9cfe-b3aeddeb2bd8" />
          <state-ref model-type="Catfish.Core.Models.Contents.Workflow.StateRef, Catfish.Core, Version=1.0.0.0, Culture=neutral, PublicKeyToken=null" id="e81de584-9d6c-4346-be1e-5b4edd601c85" ref-id="d0289864-7c3a-4394-866a-e472a6ea030d" />
          <state-ref model-type="Catfish.Core.Models.Contents.Workflow.StateRef, Catfish.Core, Version=1.0.0.0, Culture=neutral, PublicKeyToken=null" id="19b422ae-c97b-49ce-ba1f-833ab7fd9ac2" ref-id="ac42d52b-3fed-4770-9fbd-d9d5ed5d9510" />
          <state-ref model-type="Catfish.Core.Models.Contents.Workflow.StateRef, Catfish.Core, Version=1.0.0.0, Culture=neutral, PublicKeyToken=null" id="e516019d-1af2-4003-ac89-1ba8041db481" ref-id="643129b1-b5a8-4f2e-ae70-79baffc79235" />
          <state-ref model-type="Catfish.Core.Models.Contents.Workflow.StateRef, Catfish.Core, Version=1.0.0.0, Culture=neutral, PublicKeyToken=null" id="e3faf091-c4ad-4482-ae19-96d45a16137d" ref-id="7d1eeaf9-fbb4-42cd-83e4-ea6644c68a2c" />
          <state-ref model-type="Catfish.Core.Models.Contents.Workflow.StateRef, Catfish.Core, Version=1.0.0.0, Culture=neutral, PublicKeyToken=null" id="69120c5b-692f-4c42-bd64-9309efbadaf8" ref-id="467da058-6fb6-4091-b107-4837c2590033" />
          <state-ref model-type="Catfish.Core.Models.Contents.Workflow.StateRef, Catfish.Core, Version=1.0.0.0, Culture=neutral, PublicKeyToken=null" id="4eea7a04-659f-484a-a016-9c5476809d0a" ref-id="0b1f4a6f-bb5e-47e6-9a14-ea303d79f9af" />
          <state-ref model-type="Catfish.Core.Models.Contents.Workflow.StateRef, Catfish.Core, Version=1.0.0.0, Culture=neutral, PublicKeyToken=null" id="b8548d44-34c3-4574-9243-651efbf9d624" ref-id="ab79e502-c919-46bb-bc6b-16999ae9cb7b" />
          <state-ref model-type="Catfish.Core.Models.Contents.Workflow.StateRef, Catfish.Core, Version=1.0.0.0, Culture=neutral, PublicKeyToken=null" id="2831ed11-6d3c-4f7e-9a38-09f972d70b00" ref-id="ae1edcbc-daf1-4103-a7eb-c26cc89e1f70" />
          <state-ref model-type="Catfish.Core.Models.Contents.Workflow.StateRef, Catfish.Core, Version=1.0.0.0, Culture=neutral, PublicKeyToken=null" id="25deff05-b709-49e3-bd8b-c64c4a0b3753" ref-id="b64f4bc2-6759-49dd-9316-06563b8be43d" />
        </states>
        <authorizations>
          <role-ref model-type="Catfish.Core.Models.Contents.Workflow.RoleReference, Catfish.Core, Version=1.0.0.0, Culture=neutral, PublicKeyToken=null" id="74ef01f5-1de5-46d4-921a-2c34808390b6" ref-id="0f9b9e8e-ad62-478d-ad7f-ed3016c89924" />
        </authorizations>
      </get-action>
      <get-action model-type="Catfish.Core.Models.Contents.Workflow.GetAction, Catfish.Core, Version=1.0.0.0, Culture=neutral, PublicKeyToken=null" id="733a7271-e05c-404e-b94e-fa1721d13374" link-lable="Delete Submission" function="Delete" group="Details">
        <params />
        <post-actions>
          <post-action model-type="Catfish.Core.Models.Contents.Workflow.PostAction, Catfish.Core, Version=1.0.0.0, Culture=neutral, PublicKeyToken=null" id="606b4c4b-85c0-4a3a-9326-bccf9997256c" button-lable="Delete" function="Save">
            <state-mappings>
              <mapping model-type="Catfish.Core.Models.Contents.Workflow.Mapping, Catfish.Core, Version=1.0.0.0, Culture=neutral, PublicKeyToken=null" id="cc374d96-834d-4b4e-bedd-ade11aacb162" current="99c282ec-facf-4162-a615-fbf4d4881f27" next="85c1a6c0-6a48-4498-9de3-f7441c02a1bc" button-label="Delete" />
              <mapping model-type="Catfish.Core.Models.Contents.Workflow.Mapping, Catfish.Core, Version=1.0.0.0, Culture=neutral, PublicKeyToken=null" id="bebdbcd6-3986-4eb5-af3f-b258988d1e4f" current="85c1a6c0-6a48-4498-9de3-f7441c02a1bc" next="0341a706-2266-4b89-a529-7d6122c30f04" button-label="Purge" />
            </state-mappings>
            <pop-ups>
              <pop-up model-type="Catfish.Core.Models.Contents.Workflow.PopUp, Catfish.Core, Version=1.0.0.0, Culture=neutral, PublicKeyToken=null" id="2bdfe004-a796-4939-81d7-aaa14692fd9d" title="WARNING: Delete" message="Deleting the submission. Please confirm.">
                <buttons>
                  <button model-type="Catfish.Core.Models.Contents.Workflow.Button, Catfish.Core, Version=1.0.0.0, Culture=neutral, PublicKeyToken=null" id="4687a2fb-2856-45a2-a58d-7f9185b1854e" text="Yes, delete" return="true" />
                  <button model-type="Catfish.Core.Models.Contents.Workflow.Button, Catfish.Core, Version=1.0.0.0, Culture=neutral, PublicKeyToken=null" id="d2228c7b-ebb7-4980-a047-2928ff5f75ec" text="Cancel" return="false" />
                </buttons>
              </pop-up>
            </pop-ups>
            <trigger-refs />
          </post-action>
        </post-actions>
        <states>
          <state-ref model-type="Catfish.Core.Models.Contents.Workflow.StateRef, Catfish.Core, Version=1.0.0.0, Culture=neutral, PublicKeyToken=null" id="647352ac-9dd2-49cb-a6c8-2829184af697" ref-id="99c282ec-facf-4162-a615-fbf4d4881f27" />
        </states>
        <authorizations>
          <role-ref model-type="Catfish.Core.Models.Contents.Workflow.RoleReference, Catfish.Core, Version=1.0.0.0, Culture=neutral, PublicKeyToken=null" id="810a6089-8190-49dd-9dab-77aef53a0b08" ref-id="99751826-cfb9-40b0-88e0-320f54c37af0" />
        </authorizations>
      </get-action>
      <get-action model-type="Catfish.Core.Models.Contents.Workflow.GetAction, Catfish.Core, Version=1.0.0.0, Culture=neutral, PublicKeyToken=null" id="1fe2e322-4a98-464b-9d90-f1f45f88ffd2" link-lable="Purge Submission" function="Purge" group="Details">
        <params />
        <post-actions>
          <post-action model-type="Catfish.Core.Models.Contents.Workflow.PostAction, Catfish.Core, Version=1.0.0.0, Culture=neutral, PublicKeyToken=null" id="1167d497-4e0e-438b-a6ac-470216b58f58" button-lable="Purge" function="Purge">
            <state-mappings />
            <pop-ups>
              <pop-up model-type="Catfish.Core.Models.Contents.Workflow.PopUp, Catfish.Core, Version=1.0.0.0, Culture=neutral, PublicKeyToken=null" id="70107d5e-ea32-440f-815d-8afee3a9949e" title="WARNING: Deleting Permanently" message="When purged, the document cannot be recovered. Please confirm.">
                <buttons>
                  <button model-type="Catfish.Core.Models.Contents.Workflow.Button, Catfish.Core, Version=1.0.0.0, Culture=neutral, PublicKeyToken=null" id="fd33190e-efb8-47e4-8d0f-bc840b39ca97" text="Yes, purge" return="true" />
                  <button model-type="Catfish.Core.Models.Contents.Workflow.Button, Catfish.Core, Version=1.0.0.0, Culture=neutral, PublicKeyToken=null" id="6f7236fa-24d6-423c-bbc3-87cd12b6eaf2" text="Cancel" return="false" />
                </buttons>
              </pop-up>
            </pop-ups>
            <trigger-refs />
          </post-action>
        </post-actions>
        <states>
          <state-ref model-type="Catfish.Core.Models.Contents.Workflow.StateRef, Catfish.Core, Version=1.0.0.0, Culture=neutral, PublicKeyToken=null" id="b3e15962-5436-49ec-a0da-11496ce02dc1" ref-id="85c1a6c0-6a48-4498-9de3-f7441c02a1bc" />
        </states>
        <authorizations>
          <role-ref model-type="Catfish.Core.Models.Contents.Workflow.RoleReference, Catfish.Core, Version=1.0.0.0, Culture=neutral, PublicKeyToken=null" id="29f41cb1-f8a5-4483-87a2-13a914848023" ref-id="99751826-cfb9-40b0-88e0-320f54c37af0" />
        </authorizations>
      </get-action>
      <get-action model-type="Catfish.Core.Models.Contents.Workflow.GetAction, Catfish.Core, Version=1.0.0.0, Culture=neutral, PublicKeyToken=null" id="79fb396d-ee0e-4449-a928-c2e172518d41" link-lable="Send for Revision" function="ChangeState" group="Details">
        <params>
          <param model-type="Catfish.Core.Models.Contents.Workflow.Param, Catfish.Core, Version=1.0.0.0, Culture=neutral, PublicKeyToken=null" id="0c30223f-c0a2-4476-81be-bd1728330565" template-id="8c12cd83-0c37-4949-87f1-ceed634b6036" />
        </params>
        <post-actions>
          <post-action model-type="Catfish.Core.Models.Contents.Workflow.PostAction, Catfish.Core, Version=1.0.0.0, Culture=neutral, PublicKeyToken=null" id="d424d8c3-5350-40d4-a5bd-89a5267814c8" button-lable="Send for Revision" function="ChangeState">
            <state-mappings>
              <mapping model-type="Catfish.Core.Models.Contents.Workflow.Mapping, Catfish.Core, Version=1.0.0.0, Culture=neutral, PublicKeyToken=null" id="3e9c8b94-d4f2-4881-86a6-61038f6ac2f4" current="84226058-b83c-4798-87de-d0750968dea5" next="75464e92-a950-4ac4-9cfe-b3aeddeb2bd8" button-label="Send for Revision" />
              <mapping model-type="Catfish.Core.Models.Contents.Workflow.Mapping, Catfish.Core, Version=1.0.0.0, Culture=neutral, PublicKeyToken=null" id="07a886fa-b77c-4a15-9d7d-b6e3a0ebea67" current="dd21505a-f54a-4ef7-9e6e-979132dfda36" next="ac42d52b-3fed-4770-9fbd-d9d5ed5d9510" button-label="Send for Revision" />
              <mapping model-type="Catfish.Core.Models.Contents.Workflow.Mapping, Catfish.Core, Version=1.0.0.0, Culture=neutral, PublicKeyToken=null" id="e2bf76ea-69fa-4245-a040-023be0caabc1" current="db5cec7f-9b35-4d1d-9eac-f722744c9433" next="7d1eeaf9-fbb4-42cd-83e4-ea6644c68a2c" button-label="Send for Revision" />
              <mapping model-type="Catfish.Core.Models.Contents.Workflow.Mapping, Catfish.Core, Version=1.0.0.0, Culture=neutral, PublicKeyToken=null" id="87e3d4bb-3d77-4bee-abe6-e4f8e6ac6a9f" current="78d3fea4-718b-4321-b22e-10caeec498fc" next="0b1f4a6f-bb5e-47e6-9a14-ea303d79f9af" button-label="Send for Revision" />
              <mapping model-type="Catfish.Core.Models.Contents.Workflow.Mapping, Catfish.Core, Version=1.0.0.0, Culture=neutral, PublicKeyToken=null" id="51ed7f46-2c30-46a9-819b-feb3ab94398f" current="9e1956da-37bf-4bca-a577-ba561e08ff7a" next="ae1edcbc-daf1-4103-a7eb-c26cc89e1f70" button-label="Send for Revision" />
              <mapping model-type="Catfish.Core.Models.Contents.Workflow.Mapping, Catfish.Core, Version=1.0.0.0, Culture=neutral, PublicKeyToken=null" id="a81c156e-e0c5-4056-b10f-b2b9b7f7180f" current="3d73e38f-8b6a-4d71-bae1-f532de3fd67c" next="75464e92-a950-4ac4-9cfe-b3aeddeb2bd8" button-label="Send for Revision" />
              <mapping model-type="Catfish.Core.Models.Contents.Workflow.Mapping, Catfish.Core, Version=1.0.0.0, Culture=neutral, PublicKeyToken=null" id="b8f90a88-c894-41f2-ab72-f5a3cf8b11da" current="4a1c34cc-2e55-4301-9bf5-a87a5ed244f1" next="ac42d52b-3fed-4770-9fbd-d9d5ed5d9510" button-label="Send for Revision" />
              <mapping model-type="Catfish.Core.Models.Contents.Workflow.Mapping, Catfish.Core, Version=1.0.0.0, Culture=neutral, PublicKeyToken=null" id="94144e01-24fc-43cc-aa09-84c55e8322c8" current="0f53d2e0-c039-4f24-bae1-99b2cf16d408" next="7d1eeaf9-fbb4-42cd-83e4-ea6644c68a2c" button-label="Send for Revision" />
              <mapping model-type="Catfish.Core.Models.Contents.Workflow.Mapping, Catfish.Core, Version=1.0.0.0, Culture=neutral, PublicKeyToken=null" id="c7315f54-d699-4f63-a32b-cd20787581f8" current="6873f55f-4bc5-4fa3-a797-f3c838d5d98e" next="0b1f4a6f-bb5e-47e6-9a14-ea303d79f9af" button-label="Send for Revision" />
              <mapping model-type="Catfish.Core.Models.Contents.Workflow.Mapping, Catfish.Core, Version=1.0.0.0, Culture=neutral, PublicKeyToken=null" id="842e2fa1-5ac7-4c1b-af9e-9646d6689a05" current="f62f14e0-58a8-490a-8862-4292b323e699" next="ae1edcbc-daf1-4103-a7eb-c26cc89e1f70" button-label="Send for Revision" />
            </state-mappings>
            <pop-ups>
              <pop-up model-type="Catfish.Core.Models.Contents.Workflow.PopUp, Catfish.Core, Version=1.0.0.0, Culture=neutral, PublicKeyToken=null" id="29b3479c-6c68-4df2-94e5-fe30ae4f4d31" title="WARNING: Revision Document" message="Do you really want to revise this document?.">
                <buttons>
                  <button model-type="Catfish.Core.Models.Contents.Workflow.Button, Catfish.Core, Version=1.0.0.0, Culture=neutral, PublicKeyToken=null" id="dee993ff-c80d-4bc4-b697-834501c76943" text="Yes" return="true" />
                  <button model-type="Catfish.Core.Models.Contents.Workflow.Button, Catfish.Core, Version=1.0.0.0, Culture=neutral, PublicKeyToken=null" id="798897a8-8677-4658-9974-ca6e90424327" text="Cancel" return="false" />
                </buttons>
              </pop-up>
            </pop-ups>
            <trigger-refs>
              <trigger-ref model-type="Catfish.Core.Models.Contents.Workflow.TriggerRef, Catfish.Core, Version=1.0.0.0, Culture=neutral, PublicKeyToken=null" id="d2db0fb6-5de0-493b-85cc-9966fea0032a" order="0" ref-id="6d2a206a-cfab-4cdc-a88c-901bea6b9f7f" />
            </trigger-refs>
          </post-action>
        </post-actions>
        <states>
          <state-ref model-type="Catfish.Core.Models.Contents.Workflow.StateRef, Catfish.Core, Version=1.0.0.0, Culture=neutral, PublicKeyToken=null" id="31a3d3fa-1579-4b50-ad2c-c85211590599" ref-id="84226058-b83c-4798-87de-d0750968dea5" />
          <state-ref model-type="Catfish.Core.Models.Contents.Workflow.StateRef, Catfish.Core, Version=1.0.0.0, Culture=neutral, PublicKeyToken=null" id="0015458b-0c18-4103-9918-748b64575b9e" ref-id="3d73e38f-8b6a-4d71-bae1-f532de3fd67c" />
          <state-ref model-type="Catfish.Core.Models.Contents.Workflow.StateRef, Catfish.Core, Version=1.0.0.0, Culture=neutral, PublicKeyToken=null" id="19432fe5-f092-441a-9743-af4beb82e441" ref-id="dd21505a-f54a-4ef7-9e6e-979132dfda36" />
          <state-ref model-type="Catfish.Core.Models.Contents.Workflow.StateRef, Catfish.Core, Version=1.0.0.0, Culture=neutral, PublicKeyToken=null" id="c48cb20f-e41b-4350-8581-5b63ad54577c" ref-id="4a1c34cc-2e55-4301-9bf5-a87a5ed244f1" />
          <state-ref model-type="Catfish.Core.Models.Contents.Workflow.StateRef, Catfish.Core, Version=1.0.0.0, Culture=neutral, PublicKeyToken=null" id="f9b3c2d1-9a50-4f31-bb45-218ea6b5f5b8" ref-id="db5cec7f-9b35-4d1d-9eac-f722744c9433" />
          <state-ref model-type="Catfish.Core.Models.Contents.Workflow.StateRef, Catfish.Core, Version=1.0.0.0, Culture=neutral, PublicKeyToken=null" id="74fa77e0-a79f-42e0-be82-decb3c35e2e7" ref-id="0f53d2e0-c039-4f24-bae1-99b2cf16d408" />
          <state-ref model-type="Catfish.Core.Models.Contents.Workflow.StateRef, Catfish.Core, Version=1.0.0.0, Culture=neutral, PublicKeyToken=null" id="cf60f2d2-75dc-40ad-83e9-57b5b4db4189" ref-id="78d3fea4-718b-4321-b22e-10caeec498fc" />
          <state-ref model-type="Catfish.Core.Models.Contents.Workflow.StateRef, Catfish.Core, Version=1.0.0.0, Culture=neutral, PublicKeyToken=null" id="f69c9b9e-936e-42f0-99d7-50971555962e" ref-id="6873f55f-4bc5-4fa3-a797-f3c838d5d98e" />
          <state-ref model-type="Catfish.Core.Models.Contents.Workflow.StateRef, Catfish.Core, Version=1.0.0.0, Culture=neutral, PublicKeyToken=null" id="3b90845d-c001-4f61-9964-aba6e7c7bcea" ref-id="9e1956da-37bf-4bca-a577-ba561e08ff7a" />
          <state-ref model-type="Catfish.Core.Models.Contents.Workflow.StateRef, Catfish.Core, Version=1.0.0.0, Culture=neutral, PublicKeyToken=null" id="fd1be956-7bd6-4d3a-9910-7c2929b13433" ref-id="f62f14e0-58a8-490a-8862-4292b323e699" />
        </states>
        <authorizations>
          <role-ref model-type="Catfish.Core.Models.Contents.Workflow.RoleReference, Catfish.Core, Version=1.0.0.0, Culture=neutral, PublicKeyToken=null" id="b5a2cb22-f501-47e4-b190-f578a72ddb1e" ref-id="130ef6d9-033c-45b5-90d6-8c0c9ab5c50f" />
        </authorizations>
      </get-action>
      <get-action model-type="Catfish.Core.Models.Contents.Workflow.GetAction, Catfish.Core, Version=1.0.0.0, Culture=neutral, PublicKeyToken=null" id="47778b61-4df4-40f9-bb22-0c91af081690" link-lable="Update Document State" function="ChangeState" group="Details">
        <params>
          <param model-type="Catfish.Core.Models.Contents.Workflow.Param, Catfish.Core, Version=1.0.0.0, Culture=neutral, PublicKeyToken=null" id="bb564aba-3fc4-49d9-a418-326bb9e25486" template-id="8c12cd83-0c37-4949-87f1-ceed634b6036" />
        </params>
        <post-actions>
          <post-action model-type="Catfish.Core.Models.Contents.Workflow.PostAction, Catfish.Core, Version=1.0.0.0, Culture=neutral, PublicKeyToken=null" id="ffead3e0-f6c3-45f7-a20a-634e6ac78dbe" button-lable="Change State" function="Comment">
            <state-mappings>
              <mapping model-type="Catfish.Core.Models.Contents.Workflow.Mapping, Catfish.Core, Version=1.0.0.0, Culture=neutral, PublicKeyToken=null" id="62aa60a6-33bc-457d-9970-3965813caf3e" current="84226058-b83c-4798-87de-d0750968dea5" next="dd21505a-f54a-4ef7-9e6e-979132dfda36" button-label="With AAC" />
              <mapping model-type="Catfish.Core.Models.Contents.Workflow.Mapping, Catfish.Core, Version=1.0.0.0, Culture=neutral, PublicKeyToken=null" id="9a37315d-6c9f-4e93-a028-da7af1449f54" current="3d73e38f-8b6a-4d71-bae1-f532de3fd67c" next="dd21505a-f54a-4ef7-9e6e-979132dfda36" button-label="With AAC" />
              <mapping model-type="Catfish.Core.Models.Contents.Workflow.Mapping, Catfish.Core, Version=1.0.0.0, Culture=neutral, PublicKeyToken=null" id="53d39760-8a22-4e53-8223-b111e9ec729b" current="dd21505a-f54a-4ef7-9e6e-979132dfda36" next="c4ada4ca-7a2d-4831-8ab7-8c8bcff03117" button-label="AAC Approved" />
              <mapping model-type="Catfish.Core.Models.Contents.Workflow.Mapping, Catfish.Core, Version=1.0.0.0, Culture=neutral, PublicKeyToken=null" id="b1d5c6fb-9c93-4f42-8efc-42c0b5854636" current="c4ada4ca-7a2d-4831-8ab7-8c8bcff03117" next="db5cec7f-9b35-4d1d-9eac-f722744c9433" button-label="With AEC" />
              <mapping model-type="Catfish.Core.Models.Contents.Workflow.Mapping, Catfish.Core, Version=1.0.0.0, Culture=neutral, PublicKeyToken=null" id="bc21a86b-6c3f-4fd5-8fde-95de409477ee" current="db5cec7f-9b35-4d1d-9eac-f722744c9433" next="408ac0a0-31fd-4cc9-b42a-204e8aeca427" button-label="AEC Approved" />
              <mapping model-type="Catfish.Core.Models.Contents.Workflow.Mapping, Catfish.Core, Version=1.0.0.0, Culture=neutral, PublicKeyToken=null" id="c296b16a-de5a-4c60-8512-0213dd5a9def" current="4a1c34cc-2e55-4301-9bf5-a87a5ed244f1" next="dd21505a-f54a-4ef7-9e6e-979132dfda36" button-label="With AAC" />
              <mapping model-type="Catfish.Core.Models.Contents.Workflow.Mapping, Catfish.Core, Version=1.0.0.0, Culture=neutral, PublicKeyToken=null" id="fb639901-fc2e-4893-8218-2c174222573d" current="4a1c34cc-2e55-4301-9bf5-a87a5ed244f1" next="db5cec7f-9b35-4d1d-9eac-f722744c9433" button-label="With AEC" />
              <mapping model-type="Catfish.Core.Models.Contents.Workflow.Mapping, Catfish.Core, Version=1.0.0.0, Culture=neutral, PublicKeyToken=null" id="fc1438be-6aef-4d58-8ff2-dd249917b7ed" current="0f53d2e0-c039-4f24-bae1-99b2cf16d408" next="dd21505a-f54a-4ef7-9e6e-979132dfda36" button-label="With AAC" />
              <mapping model-type="Catfish.Core.Models.Contents.Workflow.Mapping, Catfish.Core, Version=1.0.0.0, Culture=neutral, PublicKeyToken=null" id="d8233b77-a302-4242-b5f5-37ca73f1150b" current="0f53d2e0-c039-4f24-bae1-99b2cf16d408" next="db5cec7f-9b35-4d1d-9eac-f722744c9433" button-label="With AEC" />
              <mapping model-type="Catfish.Core.Models.Contents.Workflow.Mapping, Catfish.Core, Version=1.0.0.0, Culture=neutral, PublicKeyToken=null" id="ef13b42e-e20f-45e7-acb5-23dc47074a5f" current="408ac0a0-31fd-4cc9-b42a-204e8aeca427" next="78d3fea4-718b-4321-b22e-10caeec498fc" button-label="With AFC" />
              <mapping model-type="Catfish.Core.Models.Contents.Workflow.Mapping, Catfish.Core, Version=1.0.0.0, Culture=neutral, PublicKeyToken=null" id="d57df0b4-0e88-405a-886f-e681b101e2fc" current="78d3fea4-718b-4321-b22e-10caeec498fc" next="8e6bb279-3a85-4892-a543-c375bf611aaf" button-label="AFC Approved" />
              <mapping model-type="Catfish.Core.Models.Contents.Workflow.Mapping, Catfish.Core, Version=1.0.0.0, Culture=neutral, PublicKeyToken=null" id="e914f51f-1552-44b6-9874-a8aabd456fba" current="0f53d2e0-c039-4f24-bae1-99b2cf16d408" next="78d3fea4-718b-4321-b22e-10caeec498fc" button-label="With AFC" />
              <mapping model-type="Catfish.Core.Models.Contents.Workflow.Mapping, Catfish.Core, Version=1.0.0.0, Culture=neutral, PublicKeyToken=null" id="a35cf5fe-f07c-4d30-9efd-9ad759b02abc" current="6873f55f-4bc5-4fa3-a797-f3c838d5d98e" next="78d3fea4-718b-4321-b22e-10caeec498fc" button-label="With AFC" />
              <mapping model-type="Catfish.Core.Models.Contents.Workflow.Mapping, Catfish.Core, Version=1.0.0.0, Culture=neutral, PublicKeyToken=null" id="f79080bf-0317-4b33-a989-d5204797a468" current="6873f55f-4bc5-4fa3-a797-f3c838d5d98e" next="db5cec7f-9b35-4d1d-9eac-f722744c9433" button-label="With AEC" />
              <mapping model-type="Catfish.Core.Models.Contents.Workflow.Mapping, Catfish.Core, Version=1.0.0.0, Culture=neutral, PublicKeyToken=null" id="2af94016-d399-428e-9794-c2355558267d" current="6873f55f-4bc5-4fa3-a797-f3c838d5d98e" next="dd21505a-f54a-4ef7-9e6e-979132dfda36" button-label="With AAC" />
              <mapping model-type="Catfish.Core.Models.Contents.Workflow.Mapping, Catfish.Core, Version=1.0.0.0, Culture=neutral, PublicKeyToken=null" id="8d572df8-31b2-416b-8353-55e3786d31d8" current="6873f55f-4bc5-4fa3-a797-f3c838d5d98e" next="8e6bb279-3a85-4892-a543-c375bf611aaf" button-label="AFC Approved" />
              <mapping model-type="Catfish.Core.Models.Contents.Workflow.Mapping, Catfish.Core, Version=1.0.0.0, Culture=neutral, PublicKeyToken=null" id="6e460592-7bf4-4f95-b141-04169b1a7b47" current="8e6bb279-3a85-4892-a543-c375bf611aaf" next="9e1956da-37bf-4bca-a577-ba561e08ff7a" button-label="With GFC" />
              <mapping model-type="Catfish.Core.Models.Contents.Workflow.Mapping, Catfish.Core, Version=1.0.0.0, Culture=neutral, PublicKeyToken=null" id="9b842453-883c-4e5c-ad53-d508c14868a9" current="9e1956da-37bf-4bca-a577-ba561e08ff7a" next="b968f9d5-0942-4c07-8f97-062ef4cd6b6b" button-label="GFC Approved" />
              <mapping model-type="Catfish.Core.Models.Contents.Workflow.Mapping, Catfish.Core, Version=1.0.0.0, Culture=neutral, PublicKeyToken=null" id="f9cb0724-bea9-4799-ab68-277f4f509f53" current="f62f14e0-58a8-490a-8862-4292b323e699" next="dd21505a-f54a-4ef7-9e6e-979132dfda36" button-label="With AAC" />
              <mapping model-type="Catfish.Core.Models.Contents.Workflow.Mapping, Catfish.Core, Version=1.0.0.0, Culture=neutral, PublicKeyToken=null" id="8f17a6ed-2bc7-49b3-863e-52943c768427" current="f62f14e0-58a8-490a-8862-4292b323e699" next="db5cec7f-9b35-4d1d-9eac-f722744c9433" button-label="With AEC" />
              <mapping model-type="Catfish.Core.Models.Contents.Workflow.Mapping, Catfish.Core, Version=1.0.0.0, Culture=neutral, PublicKeyToken=null" id="e8aa5158-dfe7-40f7-a2e0-149816fde3f9" current="f62f14e0-58a8-490a-8862-4292b323e699" next="78d3fea4-718b-4321-b22e-10caeec498fc" button-label="With AFC" />
              <mapping model-type="Catfish.Core.Models.Contents.Workflow.Mapping, Catfish.Core, Version=1.0.0.0, Culture=neutral, PublicKeyToken=null" id="8372bb8a-26e4-41b7-9942-9bb7a67f56e1" current="f62f14e0-58a8-490a-8862-4292b323e699" next="9e1956da-37bf-4bca-a577-ba561e08ff7a" button-label="With GFC" />
            </state-mappings>
            <pop-ups>
              <pop-up model-type="Catfish.Core.Models.Contents.Workflow.PopUp, Catfish.Core, Version=1.0.0.0, Culture=neutral, PublicKeyToken=null" id="7c80ef48-bdef-4a42-835c-b9ccee024cdb" title="WARNING: Change State" message="Do you really want to change the document state?.">
                <buttons>
                  <button model-type="Catfish.Core.Models.Contents.Workflow.Button, Catfish.Core, Version=1.0.0.0, Culture=neutral, PublicKeyToken=null" id="2d9b0751-fafa-415e-b3e7-a758f79d7f43" text="Yes" return="true" />
                  <button model-type="Catfish.Core.Models.Contents.Workflow.Button, Catfish.Core, Version=1.0.0.0, Culture=neutral, PublicKeyToken=null" id="e7e6c32e-24d7-4cb4-987b-343db5e51408" text="Cancel" return="false" />
                </buttons>
              </pop-up>
            </pop-ups>
            <trigger-refs />
          </post-action>
        </post-actions>
        <states>
          <state-ref model-type="Catfish.Core.Models.Contents.Workflow.StateRef, Catfish.Core, Version=1.0.0.0, Culture=neutral, PublicKeyToken=null" id="a24feb0f-496b-4b6f-ba45-11638af676eb" ref-id="84226058-b83c-4798-87de-d0750968dea5" />
          <state-ref model-type="Catfish.Core.Models.Contents.Workflow.StateRef, Catfish.Core, Version=1.0.0.0, Culture=neutral, PublicKeyToken=null" id="c839b01b-91e0-4547-b474-ad0c46b79bb6" ref-id="3d73e38f-8b6a-4d71-bae1-f532de3fd67c" />
          <state-ref model-type="Catfish.Core.Models.Contents.Workflow.StateRef, Catfish.Core, Version=1.0.0.0, Culture=neutral, PublicKeyToken=null" id="2657d13e-842e-4870-b4e3-c66a42f6e33d" ref-id="dd21505a-f54a-4ef7-9e6e-979132dfda36" />
          <state-ref model-type="Catfish.Core.Models.Contents.Workflow.StateRef, Catfish.Core, Version=1.0.0.0, Culture=neutral, PublicKeyToken=null" id="d32f9605-21cd-4027-8a31-d383dd147d2c" ref-id="4a1c34cc-2e55-4301-9bf5-a87a5ed244f1" />
          <state-ref model-type="Catfish.Core.Models.Contents.Workflow.StateRef, Catfish.Core, Version=1.0.0.0, Culture=neutral, PublicKeyToken=null" id="500736a7-25a2-466d-a2e0-e4ca56c19c98" ref-id="db5cec7f-9b35-4d1d-9eac-f722744c9433" />
          <state-ref model-type="Catfish.Core.Models.Contents.Workflow.StateRef, Catfish.Core, Version=1.0.0.0, Culture=neutral, PublicKeyToken=null" id="fbd196c3-4058-42fe-a0c6-998432c34545" ref-id="0f53d2e0-c039-4f24-bae1-99b2cf16d408" />
          <state-ref model-type="Catfish.Core.Models.Contents.Workflow.StateRef, Catfish.Core, Version=1.0.0.0, Culture=neutral, PublicKeyToken=null" id="2dbe6275-ccb0-4732-bdf1-b747ef38f8eb" ref-id="78d3fea4-718b-4321-b22e-10caeec498fc" />
          <state-ref model-type="Catfish.Core.Models.Contents.Workflow.StateRef, Catfish.Core, Version=1.0.0.0, Culture=neutral, PublicKeyToken=null" id="16b031fd-262a-41ce-aa77-14d72c47a457" ref-id="6873f55f-4bc5-4fa3-a797-f3c838d5d98e" />
          <state-ref model-type="Catfish.Core.Models.Contents.Workflow.StateRef, Catfish.Core, Version=1.0.0.0, Culture=neutral, PublicKeyToken=null" id="b3112200-5a5f-4a63-b0d8-e02d720070c4" ref-id="9e1956da-37bf-4bca-a577-ba561e08ff7a" />
          <state-ref model-type="Catfish.Core.Models.Contents.Workflow.StateRef, Catfish.Core, Version=1.0.0.0, Culture=neutral, PublicKeyToken=null" id="018fa292-fc36-4265-88b4-62e59c0e938b" ref-id="f62f14e0-58a8-490a-8862-4292b323e699" />
          <state-ref model-type="Catfish.Core.Models.Contents.Workflow.StateRef, Catfish.Core, Version=1.0.0.0, Culture=neutral, PublicKeyToken=null" id="48582cff-c310-49c3-8f44-cdacbe7e6dfe" ref-id="c4ada4ca-7a2d-4831-8ab7-8c8bcff03117" />
          <state-ref model-type="Catfish.Core.Models.Contents.Workflow.StateRef, Catfish.Core, Version=1.0.0.0, Culture=neutral, PublicKeyToken=null" id="56a82e08-f4b3-41f6-85b5-dd80b9003239" ref-id="408ac0a0-31fd-4cc9-b42a-204e8aeca427" />
          <state-ref model-type="Catfish.Core.Models.Contents.Workflow.StateRef, Catfish.Core, Version=1.0.0.0, Culture=neutral, PublicKeyToken=null" id="95faef45-843d-4b65-80fa-c8ce783c786b" ref-id="8e6bb279-3a85-4892-a543-c375bf611aaf" />
          <state-ref model-type="Catfish.Core.Models.Contents.Workflow.StateRef, Catfish.Core, Version=1.0.0.0, Culture=neutral, PublicKeyToken=null" id="c4c9dacb-c82e-4676-aa63-2ad44be87f58" ref-id="b968f9d5-0942-4c07-8f97-062ef4cd6b6b" />
        </states>
        <authorizations>
          <role-ref model-type="Catfish.Core.Models.Contents.Workflow.RoleReference, Catfish.Core, Version=1.0.0.0, Culture=neutral, PublicKeyToken=null" id="0c539207-0412-4f7a-88b4-fd866c5a3628" ref-id="130ef6d9-033c-45b5-90d6-8c0c9ab5c50f" />
        </authorizations>
      </get-action>
      <get-action model-type="Catfish.Core.Models.Contents.Workflow.GetAction, Catfish.Core, Version=1.0.0.0, Culture=neutral, PublicKeyToken=null" id="c3c32ed5-d43b-4d1e-bbac-c94d0b9959b6" link-lable="Move to Draft Calendar" function="ChangeState" group="Details">
        <params>
          <param model-type="Catfish.Core.Models.Contents.Workflow.Param, Catfish.Core, Version=1.0.0.0, Culture=neutral, PublicKeyToken=null" id="028a835c-d132-4f9d-8eaf-c15c7bdd8c80" template-id="8c12cd83-0c37-4949-87f1-ceed634b6036" />
        </params>
        <post-actions>
          <post-action model-type="Catfish.Core.Models.Contents.Workflow.PostAction, Catfish.Core, Version=1.0.0.0, Culture=neutral, PublicKeyToken=null" id="aa70d725-47eb-45b8-ae46-da9d9f26c35d" button-lable="Correct" function="Comment">
            <state-mappings>
              <mapping model-type="Catfish.Core.Models.Contents.Workflow.Mapping, Catfish.Core, Version=1.0.0.0, Culture=neutral, PublicKeyToken=null" id="d6e0d48d-e486-4515-8aef-e3f3c0e0bb42" current="b968f9d5-0942-4c07-8f97-062ef4cd6b6b" next="1a283c22-330e-4faf-9b32-fcbd8b98db80" button-label="Move To Draft Correct" />
              <mapping model-type="Catfish.Core.Models.Contents.Workflow.Mapping, Catfish.Core, Version=1.0.0.0, Culture=neutral, PublicKeyToken=null" id="f09488a7-3adf-4a55-b862-eabbb356dad3" current="e13337a0-d429-4e70-9aea-7f6d4aca20db" next="1a283c22-330e-4faf-9b32-fcbd8b98db80" button-label="Move To Draft Correct" />
            </state-mappings>
            <pop-ups>
              <pop-up model-type="Catfish.Core.Models.Contents.Workflow.PopUp, Catfish.Core, Version=1.0.0.0, Culture=neutral, PublicKeyToken=null" id="6b8773de-e8a9-4fd5-9619-0e8666e5d2de" title="WARNING: In the Draft Calendar -  Correct" message="Do you really want to change the document state?.">
                <buttons>
                  <button model-type="Catfish.Core.Models.Contents.Workflow.Button, Catfish.Core, Version=1.0.0.0, Culture=neutral, PublicKeyToken=null" id="4474d98b-5c55-4f6e-867a-47f725df29e4" text="Yes" return="true" />
                  <button model-type="Catfish.Core.Models.Contents.Workflow.Button, Catfish.Core, Version=1.0.0.0, Culture=neutral, PublicKeyToken=null" id="3f387d27-ed7c-487f-9ceb-3961eaae5bf1" text="Cancel" return="false" />
                </buttons>
              </pop-up>
            </pop-ups>
            <trigger-refs>
              <trigger-ref model-type="Catfish.Core.Models.Contents.Workflow.TriggerRef, Catfish.Core, Version=1.0.0.0, Culture=neutral, PublicKeyToken=null" id="f51a9b4f-bb38-45ed-acae-eabc72609ae4" order="0" ref-id="27227101-529f-47c1-9b21-919bb4b9790a" />
            </trigger-refs>
          </post-action>
          <post-action model-type="Catfish.Core.Models.Contents.Workflow.PostAction, Catfish.Core, Version=1.0.0.0, Culture=neutral, PublicKeyToken=null" id="0f857521-4df8-4dd3-aae5-6342be3826b1" button-lable="With Error" function="Comment">
            <state-mappings>
              <mapping model-type="Catfish.Core.Models.Contents.Workflow.Mapping, Catfish.Core, Version=1.0.0.0, Culture=neutral, PublicKeyToken=null" id="d8f729de-71d3-4a1d-9a70-db0c3330a7b1" current="e13337a0-d429-4e70-9aea-7f6d4aca20db" next="1a283c22-330e-4faf-9b32-fcbd8b98db80" button-label="Move To Draft Correct" />
            </state-mappings>
            <pop-ups>
              <pop-up model-type="Catfish.Core.Models.Contents.Workflow.PopUp, Catfish.Core, Version=1.0.0.0, Culture=neutral, PublicKeyToken=null" id="d6c54d40-7554-4625-b8c8-eb2d4f59a80d" title="WARNING: In the Draft Calendar -  Error" message="Do you really want to change the document state?.">
                <buttons>
                  <button model-type="Catfish.Core.Models.Contents.Workflow.Button, Catfish.Core, Version=1.0.0.0, Culture=neutral, PublicKeyToken=null" id="7a1e40c3-030e-4a64-ab2a-0aaab7fd2504" text="Yes" return="true" />
                  <button model-type="Catfish.Core.Models.Contents.Workflow.Button, Catfish.Core, Version=1.0.0.0, Culture=neutral, PublicKeyToken=null" id="16e9e98f-9d50-4a92-b892-398d990b0b4c" text="Cancel" return="false" />
                </buttons>
              </pop-up>
            </pop-ups>
            <trigger-refs>
              <trigger-ref model-type="Catfish.Core.Models.Contents.Workflow.TriggerRef, Catfish.Core, Version=1.0.0.0, Culture=neutral, PublicKeyToken=null" id="daffb2fb-8773-46c1-b702-f91b4477b60d" order="0" ref-id="27227101-529f-47c1-9b21-919bb4b9790a" />
            </trigger-refs>
          </post-action>
        </post-actions>
        <states>
          <state-ref model-type="Catfish.Core.Models.Contents.Workflow.StateRef, Catfish.Core, Version=1.0.0.0, Culture=neutral, PublicKeyToken=null" id="21f15416-5369-4fcb-8040-62b787a5852c" ref-id="b968f9d5-0942-4c07-8f97-062ef4cd6b6b" />
          <state-ref model-type="Catfish.Core.Models.Contents.Workflow.StateRef, Catfish.Core, Version=1.0.0.0, Culture=neutral, PublicKeyToken=null" id="bf0844f8-7ea9-47fe-866d-87992a075da2" ref-id="e13337a0-d429-4e70-9aea-7f6d4aca20db" />
        </states>
        <authorizations>
          <role-ref model-type="Catfish.Core.Models.Contents.Workflow.RoleReference, Catfish.Core, Version=1.0.0.0, Culture=neutral, PublicKeyToken=null" id="3ed7b216-bd35-4c5d-ba5e-8c0a8dc75cae" ref-id="130ef6d9-033c-45b5-90d6-8c0c9ab5c50f" />
        </authorizations>
      </get-action>
    </actions>
  </workflow>
</entity>